[
  {
    "id": "dt_mc_20250824200032ge05e",
    "timestamp": 1756368000,
    "datetime_utc": "2025-08-28T08:00:00+00:00",
    "tournament": "Cis Battle S2",
    "team1": "Runa",
    "team2": "Yes",
    "best_type": "BO3",
    "status": "已结束",
    "result": "2-1",
    "status_code": "2",
    "api_status": 2,
    "tournament_id": "dt_tt_202508241956513bqtk",
    "game_type": "Dota 2",
    "grade": "",
    "star": "",
    "bo": "",
    "map_info": "",
    "round_name": "",
    "stage_desc": "小组赛",
    "team1_logo": "https://oss.5eplay.com/cloudx/p/sport/dota2/team/d1bmfgcconkt3legelqg.png",
    "team2_logo": "https://oss.5eplay.com/sport/dota/team/575ccae50f19707d7a7cb80775da0553.png",
    "tournament_logo": "https://oss.5eplay.com/cloudx/p/sport/dota2/tournament/d253994conkt3legeumg.png"
  },
  {
    "id": "dt_mc_202508242000329fk4o",
    "timestamp": 1756370040,
    "datetime_utc": "2025-08-28T08:34:00+00:00",
    "tournament": "Cis Battle S2",
    "team1": "Z10",
    "team2": "YeS",
    "best_type": "BO3",
    "status": "已结束",
    "result": "1-2",
    "status_code": "2",
    "api_status": 2,
    "tournament_id": "dt_tt_202508241956513bqtk",
    "game_type": "Dota 2",
    "grade": "",
    "star": "",
    "bo": "",
    "map_info": "",
    "round_name": "",
    "stage_desc": "小组赛",
    "team1_logo": "https://oss.5eplay.com/cloudx/p/sport/dota2/team/csqthakconkotam81g60.png",
    "team2_logo": "https://oss.5eplay.com/cloudx/p/sport/dota2/team/ctva8tcconkqmjpn7oag.png",
    "tournament_logo": "https://oss.5eplay.com/cloudx/p/sport/dota2/tournament/d253994conkt3legeumg.png"
  },
  {
    "id": "dt_mc_202508242000328u008",
    "timestamp": 1756390200,
    "datetime_utc": "2025-08-28T14:10:00+00:00",
    "tournament": "Cis Battle S2",
    "team1": "L1ga",
    "team2": "Z10",
    "best_type": "BO3",
    "status": "已结束",
    "result": "2-0",
    "status_code": "2",
    "api_status": 2,
    "tournament_id": "dt_tt_202508241956513bqtk",
    "game_type": "Dota 2",
    "grade": "",
    "star": "",
    "bo": "",
    "map_info": "",
    "round_name": "",
    "stage_desc": "小组赛",
    "team1_logo": "https://oss.5eplay.com/cloudx/p/sport/dota2/team/merge_cn03t4sconkqks63dt3g.png",
    "team2_logo": "https://oss.5eplay.com/cloudx/p/sport/dota2/team/csqthakconkotam81g60.png",
    "tournament_logo": "https://oss.5eplay.com/cloudx/p/sport/dota2/tournament/d253994conkt3legeumg.png"
  },
  {
    "id": "dt_mc_20250824200253bygxi",
    "timestamp": 1756400400,
    "datetime_utc": "2025-08-28T17:00:00+00:00",
    "tournament": "Cis Battle S2",
    "team1": "4P",
    "team2": "Kalmychata",
    "best_type": "BO3",
    "status": "已结束",
    "result": "0-2",
    "status_code": "2",
    "api_status": 2,
    "tournament_id": "dt_tt_202508241956513bqtk",
    "game_type": "Dota 2",
    "grade": "",
    "star": "",
    "bo": "",
    "map_info": "",
    "round_name": "",
    "stage_desc": "小组赛",
    "team1_logo": "https://oss.5eplay.com/cloudx/p/sport/dota2/team/ctcl77cconkqmjpn7ek0.png",
    "team2_logo": "https://oss.5eplay.com/cloudx/p/sport/dota2/team/cnp9r1kconklgsjvgnp0.png",
    "tournament_logo": "https://oss.5eplay.com/cloudx/p/sport/dota2/tournament/d253994conkt3legeumg.png"
  },
  {
    "id": "dt_mc_202508231359527swm3",
    "timestamp": 1756436640,
    "datetime_utc": "2025-08-29T03:04:00+00:00",
    "tournament": "欧洲职业联赛 世界系列赛：东南亚 第八季",
    "team1": "Veroja",
    "team2": "MongolZ",
    "best_type": "BO3",
    "status": "已结束",
    "result": "1-2",
    "status_code": "2",
    "api_status": 2,
    "tournament_id": "dt_tt_20250823125651vnhby",
    "game_type": "Dota 2",
    "grade": "其他",
    "star": "",
    "bo": "",
    "map_info": "",
    "round_name": "",
    "stage_desc": "小组赛",
    "team1_logo": "https://oss.5eplay.com/cloudx/p/sport/dota2/team/d2kkc2sconkqbk3bnkt0.png",
    "team2_logo": "https://oss.5eplay.com/cloudx/p/sport/dota2/team/csos9icconkotam81eag.png",
    "tournament_logo": "https://oss.5eplay.com/cloudx/p/sport/dota2/tournament/d2kknk4conkqbk3bnktg.png"
  },
  {
    "id": "dt_mc_202508231302531hnzw",
    "timestamp": 1756449720,
    "datetime_utc": "2025-08-29T06:42:00+00:00",
    "tournament": "欧洲职业联赛 世界系列赛：东南亚 第八季",
    "team1": "CARST",
    "team2": "Ivory",
    "best_type": "BO3",
    "status": "已结束",
    "result": "0-2",
    "status_code": "2",
    "api_status": 2,
    "tournament_id": "dt_tt_20250823125651vnhby",
    "game_type": "Dota 2",
    "grade": "其他",
    "star": "",
    "bo": "",
    "map_info": "",
    "round_name": "",
    "stage_desc": "小组赛",
    "team1_logo": "https://oss.5eplay.com/sport/dota2/team/cgcinf1ll806h1bg2m3g.png",
    "team2_logo": "https://oss.5eplay.com/cloudx/p/sport/dota2/team/ctgdnp4conkqmjpn7gi0.png",
    "tournament_logo": "https://oss.5eplay.com/cloudx/p/sport/dota2/tournament/d2kknk4conkqbk3bnktg.png"
  },
  {
    "id": "dt_mc_20250824200033l2v03",
    "timestamp": 1756454400,
    "datetime_utc": "2025-08-29T08:00:00+00:00",
    "tournament": "Cis Battle S2",
    "team1": "4P",
    "team2": "eSpoiled",
    "best_type": "BO3",
    "status": "已结束",
    "result": "2-1",
    "status_code": "2",
    "api_status": 2,
    "tournament_id": "dt_tt_202508241956513bqtk",
    "game_type": "Dota 2",
    "grade": "",
    "star": "",
    "bo": "",
    "map_info": "",
    "round_name": "",
    "stage_desc": "小组赛",
    "team1_logo": "https://oss.5eplay.com/cloudx/p/sport/dota2/team/ctcl77cconkqmjpn7ek0.png",
    "team2_logo": "https://oss.5eplay.com/cloudx/p/sport/dota2/team/d1bmf9kconkt3legelpg.png",
    "tournament_logo": "https://oss.5eplay.com/cloudx/p/sport/dota2/tournament/d253994conkt3legeumg.png"
  },
  {
    "id": "dt_mc_20250824201003ewr0m",
    "timestamp": 1756466640,
    "datetime_utc": "2025-08-29T11:24:00+00:00",
    "tournament": "Cis Battle S2",
    "team1": "4P",
    "team2": "Z10",
    "best_type": "BO3",
    "status": "已结束",
    "result": "2-0",
    "status_code": "2",
    "api_status": 2,
    "tournament_id": "dt_tt_202508241956513bqtk",
    "game_type": "Dota 2",
    "grade": "",
    "star": "",
    "bo": "",
    "map_info": "",
    "round_name": "",
    "stage_desc": "小组赛",
    "team1_logo": "https://oss.5eplay.com/cloudx/p/sport/dota2/team/ctcl77cconkqmjpn7ek0.png",
    "team2_logo": "https://oss.5eplay.com/cloudx/p/sport/dota2/team/csqthakconkotam81g60.png",
    "tournament_logo": "https://oss.5eplay.com/cloudx/p/sport/dota2/tournament/d253994conkt3legeumg.png"
  },
  {
    "id": "dt_mc_20250824200254i9uif",
    "timestamp": 1756476600,
    "datetime_utc": "2025-08-29T14:10:00+00:00",
    "tournament": "Cis Battle S2",
    "team1": "L1ga",
    "team2": "Yes",
    "best_type": "BO3",
    "status": "已结束",
    "result": "2-0",
    "status_code": "2",
    "api_status": 2,
    "tournament_id": "dt_tt_202508241956513bqtk",
    "game_type": "Dota 2",
    "grade": "",
    "star": "",
    "bo": "",
    "map_info": "",
    "round_name": "",
    "stage_desc": "小组赛",
    "team1_logo": "https://oss.5eplay.com/cloudx/p/sport/dota2/team/merge_cn03t4sconkqks63dt3g.png",
    "team2_logo": "https://oss.5eplay.com/sport/dota/team/575ccae50f19707d7a7cb80775da0553.png",
    "tournament_logo": "https://oss.5eplay.com/cloudx/p/sport/dota2/tournament/d253994conkt3legeumg.png"
  },
  {
    "id": "dt_mc_202508242002555892k",
    "timestamp": 1756487400,
    "datetime_utc": "2025-08-29T17:10:00+00:00",
    "tournament": "Cis Battle S2",
    "team1": "Yes",
    "team2": "Kalmychata",
    "best_type": "BO3",
    "status": "已结束",
    "result": "0-2",
    "status_code": "2",
    "api_status": 2,
    "tournament_id": "dt_tt_202508241956513bqtk",
    "game_type": "Dota 2",
    "grade": "",
    "star": "",
    "bo": "",
    "map_info": "",
    "round_name": "",
    "stage_desc": "小组赛",
    "team1_logo": "https://oss.5eplay.com/sport/dota/team/575ccae50f19707d7a7cb80775da0553.png",
    "team2_logo": "https://oss.5eplay.com/cloudx/p/sport/dota2/team/cnp9r1kconklgsjvgnp0.png",
    "tournament_logo": "https://oss.5eplay.com/cloudx/p/sport/dota2/tournament/d253994conkt3legeumg.png"
  },
  {
    "id": "dt_mc_20250823125957uw57h",
    "timestamp": 1756522920,
    "datetime_utc": "2025-08-30T03:02:00+00:00",
    "tournament": "欧洲职业联赛 世界系列赛：东南亚 第八季",
    "team1": "Veroja",
    "team2": "Ivory",
    "best_type": "BO3",
    "status": "已结束",
    "result": "0-2",
    "status_code": "2",
    "api_status": 2,
    "tournament_id": "dt_tt_20250823125651vnhby",
    "game_type": "Dota 2",
    "grade": "其他",
    "star": "",
    "bo": "",
    "map_info": "",
    "round_name": "",
    "stage_desc": "小组赛",
    "team1_logo": "https://oss.5eplay.com/cloudx/p/sport/dota2/team/d2kkc2sconkqbk3bnkt0.png",
    "team2_logo": "https://oss.5eplay.com/cloudx/p/sport/dota2/team/ctgdnp4conkqmjpn7gi0.png",
    "tournament_logo": "https://oss.5eplay.com/cloudx/p/sport/dota2/tournament/d2kknk4conkqbk3bnktg.png"
  },
  {
    "id": "dt_mc_20250823143259fwcgh",
    "timestamp": 1756533600,
    "datetime_utc": "2025-08-30T06:00:00+00:00",
    "tournament": "欧洲职业联赛 世界系列赛：东南亚 第八季",
    "team1": "REKONIX",
    "team2": "Kopite",
    "best_type": "BO3",
    "status": "已结束",
    "result": "0-2",
    "status_code": "2",
    "api_status": 2,
    "tournament_id": "dt_tt_20250823125651vnhby",
    "game_type": "Dota 2",
    "grade": "其他",
    "star": "",
    "bo": "",
    "map_info": "",
    "round_name": "",
    "stage_desc": "小组赛",
    "team1_logo": "https://oss.5eplay.com/cloudx/p/sport/dota2/team/d1v23qsconkt3legesr0.png",
    "team2_logo": "https://oss.5eplay.com/cloudx/p/sport/dota2/team/d0uo9gkconkt3legefu0.png",
    "tournament_logo": "https://oss.5eplay.com/cloudx/p/sport/dota2/tournament/d2kknk4conkqbk3bnktg.png"
  },
  {
    "id": "dt_mc_20250824200255v0vno",
    "timestamp": 1756539060,
    "datetime_utc": "2025-08-30T07:31:00+00:00",
    "tournament": "Cis Battle S2",
    "team1": "eSpoiled",
    "team2": "YeS",
    "best_type": "BO3",
    "status": "已结束",
    "result": "1-2",
    "status_code": "2",
    "api_status": 2,
    "tournament_id": "dt_tt_202508241956513bqtk",
    "game_type": "Dota 2",
    "grade": "",
    "star": "",
    "bo": "",
    "map_info": "",
    "round_name": "",
    "stage_desc": "小组赛",
    "team1_logo": "https://oss.5eplay.com/cloudx/p/sport/dota2/team/d1bmf9kconkt3legelpg.png",
    "team2_logo": "https://oss.5eplay.com/cloudx/p/sport/dota2/team/ctva8tcconkqmjpn7oag.png",
    "tournament_logo": "https://oss.5eplay.com/cloudx/p/sport/dota2/tournament/d253994conkt3legeumg.png"
  },
  {
    "id": "dt_mc_20250824200256lqfj7",
    "timestamp": 1756552200,
    "datetime_utc": "2025-08-30T11:10:00+00:00",
    "tournament": "Cis Battle S2",
    "team1": "Yes",
    "team2": "YeS",
    "best_type": "BO3",
    "status": "已结束",
    "result": "2-1",
    "status_code": "2",
    "api_status": 2,
    "tournament_id": "dt_tt_202508241956513bqtk",
    "game_type": "Dota 2",
    "grade": "",
    "star": "",
    "bo": "",
    "map_info": "",
    "round_name": "",
    "stage_desc": "小组赛",
    "team1_logo": "https://oss.5eplay.com/sport/dota/team/575ccae50f19707d7a7cb80775da0553.png",
    "team2_logo": "https://oss.5eplay.com/cloudx/p/sport/dota2/team/ctva8tcconkqmjpn7oag.png",
    "tournament_logo": "https://oss.5eplay.com/cloudx/p/sport/dota2/tournament/d253994conkt3legeumg.png"
  },
  {
    "id": "dt_mc_20250817123258ega8x",
    "timestamp": 1756555560,
    "datetime_utc": "2025-08-30T12:06:00+00:00",
    "tournament": "2025 ST锦标赛",
    "team1": "GermanIvan+4",
    "team2": "eSpoiled",
    "best_type": "BO3",
    "status": "已结束",
    "result": "1-2",
    "status_code": "2",
    "api_status": 2,
    "tournament_id": "dt_tt_2025081712205101w8k",
    "game_type": "Dota 2",
    "grade": "",
    "star": "",
    "bo": "",
    "map_info": "",
    "round_name": "决赛",
    "stage_desc": "淘汰赛 决赛",
    "team1_logo": "https://oss.5eplay.com/cloudx/p/sport/dota2/team/d2glob4conkt3legf0vg.png",
    "team2_logo": "https://oss.5eplay.com/cloudx/p/sport/dota2/team/d1bmf9kconkt3legelpg.png",
    "tournament_logo": "https://oss.5eplay.com/cloudx/p/sport/dota2/tournament/d2glta4conkt3legf120.png"
  },
  {
    "id": "dt_mc_20250824200257mji2z",
    "timestamp": 1756564200,
    "datetime_utc": "2025-08-30T14:30:00+00:00",
    "tournament": "Cis Battle S2",
    "team1": "L1ga",
    "team2": "4P",
    "best_type": "BO3",
    "status": "已结束",
    "result": "2-0",
    "status_code": "2",
    "api_status": 2,
    "tournament_id": "dt_tt_202508241956513bqtk",
    "game_type": "Dota 2",
    "grade": "",
    "star": "",
    "bo": "",
    "map_info": "",
    "round_name": "",
    "stage_desc": "小组赛",
    "team1_logo": "https://oss.5eplay.com/cloudx/p/sport/dota2/team/merge_cn03t4sconkqks63dt3g.png",
    "team2_logo": "https://oss.5eplay.com/cloudx/p/sport/dota2/team/ctcl77cconkqmjpn7ek0.png",
    "tournament_logo": "https://oss.5eplay.com/cloudx/p/sport/dota2/tournament/d253994conkt3legeumg.png"
  },
  {
    "id": "dt_mc_20250824200258j2pcl",
    "timestamp": 1756573800,
    "datetime_utc": "2025-08-30T17:10:00+00:00",
    "tournament": "Cis Battle S2",
    "team1": "4P",
    "team2": "Yes",
    "best_type": "BO3",
    "status": "已结束",
    "result": "0-2",
    "status_code": "2",
    "api_status": 2,
    "tournament_id": "dt_tt_202508241956513bqtk",
    "game_type": "Dota 2",
    "grade": "",
    "star": "",
    "bo": "",
    "map_info": "",
    "round_name": "",
    "stage_desc": "小组赛",
    "team1_logo": "https://oss.5eplay.com/cloudx/p/sport/dota2/team/ctcl77cconkqmjpn7ek0.png",
    "team2_logo": "https://oss.5eplay.com/sport/dota/team/575ccae50f19707d7a7cb80775da0553.png",
    "tournament_logo": "https://oss.5eplay.com/cloudx/p/sport/dota2/tournament/d253994conkt3legeumg.png"
  },
  {
    "id": "dt_mc_20250823130252fpkn5",
    "timestamp": 1756609500,
    "datetime_utc": "2025-08-31T03:05:00+00:00",
    "tournament": "欧洲职业联赛 世界系列赛：东南亚 第八季",
    "team1": "MongolZ",
    "team2": "Kopite",
    "best_type": "BO3",
    "status": "已结束",
    "result": "2-1",
    "status_code": "2",
    "api_status": 2,
    "tournament_id": "dt_tt_20250823125651vnhby",
    "game_type": "Dota 2",
    "grade": "其他",
    "star": "",
    "bo": "",
    "map_info": "",
    "round_name": "",
    "stage_desc": "小组赛",
    "team1_logo": "https://oss.5eplay.com/cloudx/p/sport/dota2/team/csos9icconkotam81eag.png",
    "team2_logo": "https://oss.5eplay.com/cloudx/p/sport/dota2/team/d0uo9gkconkt3legefu0.png",
    "tournament_logo": "https://oss.5eplay.com/cloudx/p/sport/dota2/tournament/d2kknk4conkqbk3bnktg.png"
  },
  {
    "id": "dt_mc_20250824200259y6wvr",
    "timestamp": 1756627800,
    "datetime_utc": "2025-08-31T08:10:00+00:00",
    "tournament": "Cis Battle S2",
    "team1": "Runa",
    "team2": "4P",
    "best_type": "BO3",
    "status": "已结束",
    "result": "0-2",
    "status_code": "2",
    "api_status": 2,
    "tournament_id": "dt_tt_202508241956513bqtk",
    "game_type": "Dota 2",
    "grade": "",
    "star": "",
    "bo": "",
    "map_info": "",
    "round_name": "",
    "stage_desc": "小组赛",
    "team1_logo": "https://oss.5eplay.com/cloudx/p/sport/dota2/team/d1bmfgcconkt3legelqg.png",
    "team2_logo": "https://oss.5eplay.com/cloudx/p/sport/dota2/team/ctcl77cconkqmjpn7ek0.png",
    "tournament_logo": "https://oss.5eplay.com/cloudx/p/sport/dota2/tournament/d253994conkt3legeumg.png"
  },
  {
    "id": "dt_mc_20250824200301edzbz",
    "timestamp": 1756638600,
    "datetime_utc": "2025-08-31T11:10:00+00:00",
    "tournament": "Cis Battle S2",
    "team1": "4P",
    "team2": "YeS",
    "best_type": "BO3",
    "status": "已结束",
    "result": "0-2",
    "status_code": "2",
    "api_status": 2,
    "tournament_id": "dt_tt_202508241956513bqtk",
    "game_type": "Dota 2",
    "grade": "",
    "star": "",
    "bo": "",
    "map_info": "",
    "round_name": "",
    "stage_desc": "小组赛",
    "team1_logo": "https://oss.5eplay.com/cloudx/p/sport/dota2/team/ctcl77cconkqmjpn7ek0.png",
    "team2_logo": "https://oss.5eplay.com/cloudx/p/sport/dota2/team/ctva8tcconkqmjpn7oag.png",
    "tournament_logo": "https://oss.5eplay.com/cloudx/p/sport/dota2/tournament/d253994conkt3legeumg.png"
  },
  {
    "id": "dt_mc_20250824203552b5twe",
    "timestamp": 1756649400,
    "datetime_utc": "2025-08-31T14:10:00+00:00",
    "tournament": "Cis Battle S2",
    "team1": "Kalmychata",
    "team2": "YeS",
    "best_type": "BO3",
    "status": "已结束",
    "result": "2-1",
    "status_code": "2",
    "api_status": 2,
    "tournament_id": "dt_tt_202508241956513bqtk",
    "game_type": "Dota 2",
    "grade": "",
    "star": "",
    "bo": "",
    "map_info": "",
    "round_name": "",
    "stage_desc": "小组赛",
    "team1_logo": "https://oss.5eplay.com/cloudx/p/sport/dota2/team/cnp9r1kconklgsjvgnp0.png",
    "team2_logo": "https://oss.5eplay.com/cloudx/p/sport/dota2/team/ctva8tcconkqmjpn7oag.png",
    "tournament_logo": "https://oss.5eplay.com/cloudx/p/sport/dota2/tournament/d253994conkt3legeumg.png"
  },
  {
    "id": "dt_mc_2025082420030109cak",
    "timestamp": 1756659960,
    "datetime_utc": "2025-08-31T17:06:00+00:00",
    "tournament": "Cis Battle S2",
    "team1": "L1ga",
    "team2": "Kalmychata",
    "best_type": "BO3",
    "status": "已结束",
    "result": "2-1",
    "status_code": "2",
    "api_status": 2,
    "tournament_id": "dt_tt_202508241956513bqtk",
    "game_type": "Dota 2",
    "grade": "",
    "star": "",
    "bo": "",
    "map_info": "",
    "round_name": "",
    "stage_desc": "小组赛",
    "team1_logo": "https://oss.5eplay.com/cloudx/p/sport/dota2/team/merge_cn03t4sconkqks63dt3g.png",
    "team2_logo": "https://oss.5eplay.com/cloudx/p/sport/dota2/team/cnp9r1kconklgsjvgnp0.png",
    "tournament_logo": "https://oss.5eplay.com/cloudx/p/sport/dota2/tournament/d253994conkt3legeumg.png"
  },
  {
    "id": "dt_mc_2025082313025413zmw",
    "timestamp": 1756695960,
    "datetime_utc": "2025-09-01T03:06:00+00:00",
    "tournament": "欧洲职业联赛 世界系列赛：东南亚 第八季",
    "team1": "REKONIX",
    "team2": "Ivory",
    "best_type": "BO3",
    "status": "已结束",
    "result": "2-1",
    "status_code": "2",
    "api_status": 2,
    "tournament_id": "dt_tt_20250823125651vnhby",
    "game_type": "Dota 2",
    "grade": "其他",
    "star": "",
    "bo": "",
    "map_info": "",
    "round_name": "",
    "stage_desc": "小组赛",
    "team1_logo": "https://oss.5eplay.com/cloudx/p/sport/dota2/team/d1v23qsconkt3legesr0.png",
    "team2_logo": "https://oss.5eplay.com/cloudx/p/sport/dota2/team/ctgdnp4conkqmjpn7gi0.png",
    "tournament_logo": "https://oss.5eplay.com/cloudx/p/sport/dota2/tournament/d2kknk4conkqbk3bnktg.png"
  },
  {
    "id": "dt_mc_20250823133252zfshq",
    "timestamp": 1756708500,
    "datetime_utc": "2025-09-01T06:35:00+00:00",
    "tournament": "欧洲职业联赛 世界系列赛：东南亚 第八季",
    "team1": "Veroja",
    "team2": "REKONIX",
    "best_type": "BO3",
    "status": "已结束",
    "result": "0-2",
    "status_code": "2",
    "api_status": 2,
    "tournament_id": "dt_tt_20250823125651vnhby",
    "game_type": "Dota 2",
    "grade": "其他",
    "star": "",
    "bo": "",
    "map_info": "",
    "round_name": "",
    "stage_desc": "小组赛",
    "team1_logo": "https://oss.5eplay.com/cloudx/p/sport/dota2/team/d2kkc2sconkqbk3bnkt0.png",
    "team2_logo": "https://oss.5eplay.com/cloudx/p/sport/dota2/team/d1v23qsconkt3legesr0.png",
    "tournament_logo": "https://oss.5eplay.com/cloudx/p/sport/dota2/tournament/d2kknk4conkqbk3bnktg.png"
  },
  {
    "id": "dt_mc_20250823130253himhw",
    "timestamp": 1756717200,
    "datetime_utc": "2025-09-01T09:00:00+00:00",
    "tournament": "欧洲职业联赛 世界系列赛：东南亚 第八季",
    "team1": "Kopite",
    "team2": "Ivory",
    "best_type": "BO3",
    "status": "已结束",
    "result": "2-0",
    "status_code": "2",
    "api_status": 2,
    "tournament_id": "dt_tt_20250823125651vnhby",
    "game_type": "Dota 2",
    "grade": "其他",
    "star": "",
    "bo": "",
    "map_info": "",
    "round_name": "",
    "stage_desc": "小组赛",
    "team1_logo": "https://oss.5eplay.com/cloudx/p/sport/dota2/team/d0uo9gkconkt3legefu0.png",
    "team2_logo": "https://oss.5eplay.com/cloudx/p/sport/dota2/team/ctgdnp4conkqmjpn7gi0.png",
    "tournament_logo": "https://oss.5eplay.com/cloudx/p/sport/dota2/tournament/d2kknk4conkqbk3bnktg.png"
  },
  {
    "id": "dt_mc_202508242003036v2oe",
    "timestamp": 1756717320,
    "datetime_utc": "2025-09-01T09:02:00+00:00",
    "tournament": "Cis Battle S2",
    "team1": "Kalmychata",
    "team2": "Yes",
    "best_type": "BO3",
    "status": "已结束",
    "result": "0-2",
    "status_code": "2",
    "api_status": 2,
    "tournament_id": "dt_tt_202508241956513bqtk",
    "game_type": "Dota 2",
    "grade": "",
    "star": "",
    "bo": "",
    "map_info": "",
    "round_name": "半决赛",
    "stage_desc": "淘汰赛 胜者组 半决赛",
    "team1_logo": "https://oss.5eplay.com/cloudx/p/sport/dota2/team/cnp9r1kconklgsjvgnp0.png",
    "team2_logo": "https://oss.5eplay.com/sport/dota/team/575ccae50f19707d7a7cb80775da0553.png",
    "tournament_logo": "https://oss.5eplay.com/cloudx/p/sport/dota2/tournament/d253994conkt3legeumg.png"
  },
  {
    "id": "dt_mc_20250824200301ksitx",
    "timestamp": 1756728000,
    "datetime_utc": "2025-09-01T12:00:00+00:00",
    "tournament": "Cis Battle S2",
    "team1": "OG",
    "team2": "L1ga",
    "best_type": "BO3",
    "status": "已结束",
    "result": "2-0",
    "status_code": "2",
    "api_status": 2,
    "tournament_id": "dt_tt_202508241956513bqtk",
    "game_type": "Dota 2",
    "grade": "",
    "star": "",
    "bo": "",
    "map_info": "",
    "round_name": "半决赛",
    "stage_desc": "淘汰赛 胜者组 半决赛",
    "team1_logo": "https://oss.5eplay.com/sport/dota/team/FotJp9DR3Rz3ky70g7ZLBRajgqPm.png",
    "team2_logo": "https://oss.5eplay.com/cloudx/p/sport/dota2/team/merge_cn03t4sconkqks63dt3g.png",
    "tournament_logo": "https://oss.5eplay.com/cloudx/p/sport/dota2/tournament/d253994conkt3legeumg.png"
  },
  {
    "id": "dt_mc_20250824200306yj5f0",
    "timestamp": 1756742400,
    "datetime_utc": "2025-09-01T16:00:00+00:00",
    "tournament": "Cis Battle S2",
    "team1": "Kalmychata",
    "team2": "4P",
    "best_type": "BO3",
    "status": "已结束",
    "result": "2-0",
    "status_code": "2",
    "api_status": 2,
    "tournament_id": "dt_tt_202508241956513bqtk",
    "game_type": "Dota 2",
    "grade": "",
    "star": "",
    "bo": "",
    "map_info": "",
    "round_name": "1/4决赛",
    "stage_desc": "淘汰赛 败者组 1/4决赛",
    "team1_logo": "https://oss.5eplay.com/cloudx/p/sport/dota2/team/cnp9r1kconklgsjvgnp0.png",
    "team2_logo": "https://oss.5eplay.com/cloudx/p/sport/dota2/team/ctcl77cconkqmjpn7ek0.png",
    "tournament_logo": "https://oss.5eplay.com/cloudx/p/sport/dota2/tournament/d253994conkt3legeumg.png"
  },
  {
    "id": "dt_mc_20250823130255l511m",
    "timestamp": 1756793220,
    "datetime_utc": "2025-09-02T06:07:00+00:00",
    "tournament": "欧洲职业联赛 世界系列赛：东南亚 第八季",
    "team1": "InterActive",
    "team2": "Veroja",
    "best_type": "BO3",
    "status": "已结束",
    "result": "1-2",
    "status_code": "2",
    "api_status": 2,
    "tournament_id": "dt_tt_20250823125651vnhby",
    "game_type": "Dota 2",
    "grade": "其他",
    "star": "",
    "bo": "",
    "map_info": "",
    "round_name": "",
    "stage_desc": "小组赛",
    "team1_logo": "https://oss.5eplay.com/cloudx/p/sport/dota2/team/cktjb3sconkqks63c510.png",
    "team2_logo": "https://oss.5eplay.com/cloudx/p/sport/dota2/team/d2kkc2sconkqbk3bnkt0.png",
    "tournament_logo": "https://oss.5eplay.com/cloudx/p/sport/dota2/tournament/d2kknk4conkqbk3bnktg.png"
  },
  {
    "id": "dt_mc_20250824200306g7gps",
    "timestamp": 1756807200,
    "datetime_utc": "2025-09-02T10:00:00+00:00",
    "tournament": "Cis Battle S2",
    "team1": "L1ga",
    "team2": "YeS",
    "best_type": "BO3",
    "status": "已结束",
    "result": "2-0",
    "status_code": "2",
    "api_status": 2,
    "tournament_id": "dt_tt_202508241956513bqtk",
    "game_type": "Dota 2",
    "grade": "",
    "star": "",
    "bo": "",
    "map_info": "",
    "round_name": "1/4决赛",
    "stage_desc": "淘汰赛 败者组 1/4决赛",
    "team1_logo": "https://oss.5eplay.com/cloudx/p/sport/dota2/team/merge_cn03t4sconkqks63dt3g.png",
    "team2_logo": "https://oss.5eplay.com/cloudx/p/sport/dota2/team/ctva8tcconkqmjpn7oag.png",
    "tournament_logo": "https://oss.5eplay.com/cloudx/p/sport/dota2/tournament/d253994conkt3legeumg.png"
  },
  {
    "id": "dt_mc_20250824200305yv3jt",
    "timestamp": 1756818900,
    "datetime_utc": "2025-09-02T13:15:00+00:00",
    "tournament": "Cis Battle S2",
    "team1": "OG",
    "team2": "Yes",
    "best_type": "BO3",
    "status": "已结束",
    "result": "2-0",
    "status_code": "2",
    "api_status": 2,
    "tournament_id": "dt_tt_202508241956513bqtk",
    "game_type": "Dota 2",
    "grade": "",
    "star": "",
    "bo": "",
    "map_info": "",
    "round_name": "决赛",
    "stage_desc": "淘汰赛 胜者组 决赛",
    "team1_logo": "https://oss.5eplay.com/sport/dota/team/FotJp9DR3Rz3ky70g7ZLBRajgqPm.png",
    "team2_logo": "https://oss.5eplay.com/sport/dota/team/575ccae50f19707d7a7cb80775da0553.png",
    "tournament_logo": "https://oss.5eplay.com/cloudx/p/sport/dota2/tournament/d253994conkt3legeumg.png"
  },
  {
    "id": "dt_mc_20250824200308hs78a",
    "timestamp": 1756829220,
    "datetime_utc": "2025-09-02T16:07:00+00:00",
    "tournament": "Cis Battle S2",
    "team1": "L1ga",
    "team2": "Kalmychata",
    "best_type": "BO3",
    "status": "已结束",
    "result": "2-1",
    "status_code": "2",
    "api_status": 2,
    "tournament_id": "dt_tt_202508241956513bqtk",
    "game_type": "Dota 2",
    "grade": "",
    "star": "",
    "bo": "",
    "map_info": "",
    "round_name": "半决赛",
    "stage_desc": "淘汰赛 败者组 半决赛",
    "team1_logo": "https://oss.5eplay.com/cloudx/p/sport/dota2/team/merge_cn03t4sconkqks63dt3g.png",
    "team2_logo": "https://oss.5eplay.com/cloudx/p/sport/dota2/team/cnp9r1kconklgsjvgnp0.png",
    "tournament_logo": "https://oss.5eplay.com/cloudx/p/sport/dota2/tournament/d253994conkt3legeumg.png"
  },
  {
    "id": "dt_mc_20250901235352fx1kc",
    "timestamp": 1756836300,
    "datetime_utc": "2025-09-02T18:05:00+00:00",
    "tournament": "ACS 系列赛 2",
    "team1": "TW",
    "team2": "OG.LATAM",
    "best_type": "BO3",
    "status": "已结束",
    "result": "0-2",
    "status_code": "2",
    "api_status": 2,
    "tournament_id": "dt_tt_20250901235351dhf4h",
    "game_type": "Dota 2",
    "grade": "",
    "star": "",
    "bo": "",
    "map_info": "",
    "round_name": "",
    "stage_desc": "小组赛",
    "team1_logo": "https://oss.5eplay.com/cloudx/p/sport/dota2/team/cr0lv4cconkotam80deg.png",
    "team2_logo": "https://oss.5eplay.com/cloudx/p/sport/dota2/team/d0ipofcconkt3legebh0.png",
    "tournament_logo": "https://oss.5eplay.com/cloudx/p/sport/dota2/tournament/d2297isconkt3legeu1g.png"
  },
  {
    "id": "dt_mc_20250901235353tqoo5",
    "timestamp": 1756847100,
    "datetime_utc": "2025-09-02T21:05:00+00:00",
    "tournament": "ACS 系列赛 2",
    "team1": "Allstars",
    "team2": "EB",
    "best_type": "BO3",
    "status": "已结束",
    "result": "0-2",
    "status_code": "2",
    "api_status": 2,
    "tournament_id": "dt_tt_20250901235351dhf4h",
    "game_type": "Dota 2",
    "grade": "",
    "star": "",
    "bo": "",
    "map_info": "",
    "round_name": "",
    "stage_desc": "小组赛",
    "team1_logo": "https://oss.5eplay.com/cloudx/p/sport/dota2/team/d1bnfnkconkt3legelsg.png",
    "team2_logo": "https://oss.5eplay.com/cloudx/p/sport/dota2/team/cm1c8ksconkqks63d3kg.png",
    "tournament_logo": "https://oss.5eplay.com/cloudx/p/sport/dota2/tournament/d2297isconkt3legeu1g.png"
  },
  {
    "id": "dt_mc_202508262038521ykod",
    "timestamp": 1756868460,
    "datetime_utc": "2025-09-03T03:01:00+00:00",
    "tournament": "欧洲职业联赛 世界系列赛：东南亚 第八季",
    "team1": "REKONIX",
    "team2": "MongolZ",
    "best_type": "BO3",
    "status": "已结束",
    "result": "2-1",
    "status_code": "2",
    "api_status": 2,
    "tournament_id": "dt_tt_20250823125651vnhby",
    "game_type": "Dota 2",
    "grade": "其他",
    "star": "",
    "bo": "",
    "map_info": "",
    "round_name": "半决赛",
    "stage_desc": "淘汰赛 胜者组 半决赛",
    "team1_logo": "https://oss.5eplay.com/cloudx/p/sport/dota2/team/d1v23qsconkt3legesr0.png",
    "team2_logo": "https://oss.5eplay.com/cloudx/p/sport/dota2/team/csos9icconkotam81eag.png",
    "tournament_logo": "https://oss.5eplay.com/cloudx/p/sport/dota2/tournament/d2kknk4conkqbk3bnktg.png"
  },
  {
    "id": "dt_mc_202508262038536sz48",
    "timestamp": 1756879800,
    "datetime_utc": "2025-09-03T06:10:00+00:00",
    "tournament": "欧洲职业联赛 世界系列赛：东南亚 第八季",
    "team1": "Kopite",
    "team2": "Ivory",
    "best_type": "BO3",
    "status": "已结束",
    "result": "1-2",
    "status_code": "2",
    "api_status": 2,
    "tournament_id": "dt_tt_20250823125651vnhby",
    "game_type": "Dota 2",
    "grade": "其他",
    "star": "",
    "bo": "",
    "map_info": "",
    "round_name": "半决赛",
    "stage_desc": "淘汰赛 胜者组 半决赛",
    "team1_logo": "https://oss.5eplay.com/cloudx/p/sport/dota2/team/d0uo9gkconkt3legefu0.png",
    "team2_logo": "https://oss.5eplay.com/cloudx/p/sport/dota2/team/ctgdnp4conkqmjpn7gi0.png",
    "tournament_logo": "https://oss.5eplay.com/cloudx/p/sport/dota2/tournament/d2kknk4conkqbk3bnktg.png"
  },
  {
    "id": "dt_mc_20250824200308nrjb1",
    "timestamp": 1756897200,
    "datetime_utc": "2025-09-03T11:00:00+00:00",
    "tournament": "Cis Battle S2",
    "team1": "Yes",
    "team2": "L1ga",
    "best_type": "BO3",
    "status": "已结束",
    "result": "0-2",
    "status_code": "2",
    "api_status": 2,
    "tournament_id": "dt_tt_202508241956513bqtk",
    "game_type": "Dota 2",
    "grade": "",
    "star": "",
    "bo": "",
    "map_info": "",
    "round_name": "决赛",
    "stage_desc": "淘汰赛 败者组 决赛",
    "team1_logo": "https://oss.5eplay.com/sport/dota/team/575ccae50f19707d7a7cb80775da0553.png",
    "team2_logo": "https://oss.5eplay.com/cloudx/p/sport/dota2/team/merge_cn03t4sconkqks63dt3g.png",
    "tournament_logo": "https://oss.5eplay.com/cloudx/p/sport/dota2/tournament/d253994conkt3legeumg.png"
  },
  {
    "id": "dt_mc_20250824200310iv1y9",
    "timestamp": 1756912200,
    "datetime_utc": "2025-09-03T15:10:00+00:00",
    "tournament": "Cis Battle S2",
    "team1": "OG",
    "team2": "L1ga",
    "best_type": "BO5",
    "status": "已结束",
    "result": "3-1",
    "status_code": "2",
    "api_status": 2,
    "tournament_id": "dt_tt_202508241956513bqtk",
    "game_type": "Dota 2",
    "grade": "",
    "star": "",
    "bo": "",
    "map_info": "",
    "round_name": "总决赛",
    "stage_desc": "淘汰赛  总决赛",
    "team1_logo": "https://oss.5eplay.com/sport/dota/team/FotJp9DR3Rz3ky70g7ZLBRajgqPm.png",
    "team2_logo": "https://oss.5eplay.com/cloudx/p/sport/dota2/team/merge_cn03t4sconkqks63dt3g.png",
    "tournament_logo": "https://oss.5eplay.com/cloudx/p/sport/dota2/tournament/d253994conkt3legeumg.png"
  },
  {
    "id": "dt_mc_20250901235354r6stm",
    "timestamp": 1756922700,
    "datetime_utc": "2025-09-03T18:05:00+00:00",
    "tournament": "ACS 系列赛 2",
    "team1": "TW",
    "team2": "Tortu Ninjas",
    "best_type": "BO3",
    "status": "已结束",
    "result": "2-0",
    "status_code": "2",
    "api_status": 2,
    "tournament_id": "dt_tt_20250901235351dhf4h",
    "game_type": "Dota 2",
    "grade": "",
    "star": "",
    "bo": "",
    "map_info": "",
    "round_name": "",
    "stage_desc": "小组赛",
    "team1_logo": "https://oss.5eplay.com/cloudx/p/sport/dota2/team/cr0lv4cconkotam80deg.png",
    "team2_logo": "https://oss.5eplay.com/cloudx/p/sport/dota2/team/d2qsilcconkqbk3bnm1g.png",
    "tournament_logo": "https://oss.5eplay.com/cloudx/p/sport/dota2/tournament/d2297isconkt3legeu1g.png"
  },
  {
    "id": "dt_mc_20250901235355ilw0e",
    "timestamp": 1756933260,
    "datetime_utc": "2025-09-03T21:01:00+00:00",
    "tournament": "ACS 系列赛 2",
    "team1": "TC",
    "team2": "Pacific",
    "best_type": "BO3",
    "status": "已结束",
    "result": "1-2",
    "status_code": "2",
    "api_status": 2,
    "tournament_id": "dt_tt_20250901235351dhf4h",
    "game_type": "Dota 2",
    "grade": "",
    "star": "",
    "bo": "",
    "map_info": "",
    "round_name": "",
    "stage_desc": "小组赛",
    "team1_logo": "https://oss.5eplay.com/cloudx/p/sport/dota2/team/cuhf0bkconkqmjpn82fg.png",
    "team2_logo": "https://oss.5eplay.com/cloudx/p/sport/dota2/team/chnhu7f4nfq3cc4uddb0.png",
    "tournament_logo": "https://oss.5eplay.com/cloudx/p/sport/dota2/tournament/d2297isconkt3legeu1g.png"
  },
  {
    "id": "dt_mc_202509021559524mhg5",
    "timestamp": 1756973100,
    "datetime_utc": "2025-09-04T08:05:00+00:00",
    "tournament": "TI14国际邀请赛",
    "team1": "Tundra",
    "team2": "YB",
    "best_type": "BO3",
    "status": "进行中",
    "result": "0-0",
    "status_code": "1",
    "api_status": 1,
    "tournament_id": "dt_tt_20250524123429r04um",
    "game_type": "Dota 2",
    "grade": "S级",
    "star": "2",
    "bo": "",
    "map_info": "",
    "round_name": "",
    "stage_desc": "小组赛",
    "team1_logo": "https://oss.5eplay.com/cloudx/p/sport/dota2/team/merge_cncb1dcconkqks63e7rg.png",
    "team2_logo": "https://oss.5eplay.com/cloudx/p/sport/dota2/team/d0e6li4conkt3lege8u0.png",
    "tournament_logo": "https://oss.5eplay.com/cloudx/p/sport/dota2/tournament/cnmju9cconklgsjvgm8g.png"
  },
  {
    "id": "dt_mc_20250902155953wdzwa",
    "timestamp": 1756973100,
    "datetime_utc": "2025-09-04T08:05:00+00:00",
    "tournament": "TI14国际邀请赛",
    "team1": "TSpirit",
    "team2": "Wildcard",
    "best_type": "BO3",
    "status": "进行中",
    "result": "0-0",
    "status_code": "1",
    "api_status": 1,
    "tournament_id": "dt_tt_20250524123429r04um",
    "game_type": "Dota 2",
    "grade": "S级",
    "star": "1",
    "bo": "",
    "map_info": "",
    "round_name": "",
    "stage_desc": "小组赛",
    "team1_logo": "https://oss.5eplay.com/cloudx/p/sport/dota2/team/merge_cncb24cconkqks63e7vg.png",
    "team2_logo": "https://oss.5eplay.com/cloudx/p/sport/dota2/team/cu0t2v4conkqmjpn7ph0.png",
    "tournament_logo": "https://oss.5eplay.com/cloudx/p/sport/dota2/tournament/cnmju9cconklgsjvgm8g.png"
  },
  {
    "id": "dt_mc_2025090215595330jqf",
    "timestamp": 1756973100,
    "datetime_utc": "2025-09-04T08:05:00+00:00",
    "tournament": "TI14国际邀请赛",
    "team1": " Falcons",
    "team2": "Nemesis",
    "best_type": "BO3",
    "status": "进行中",
    "result": "0-0",
    "status_code": "1",
    "api_status": 1,
    "tournament_id": "dt_tt_20250524123429r04um",
    "game_type": "Dota 2",
    "grade": "S级",
    "star": "1",
    "bo": "",
    "map_info": "",
    "round_name": "",
    "stage_desc": "小组赛",
    "team1_logo": "https://oss.5eplay.com/cloudx/p/sport/dota2/team/clts47sconkqks63d0k0.png",
    "team2_logo": "https://oss.5eplay.com/cloudx/p/sport/dota2/team/d2aleckconkt3legev8g.png",
    "tournament_logo": "https://oss.5eplay.com/cloudx/p/sport/dota2/tournament/cnmju9cconklgsjvgm8g.png"
  },
  {
    "id": "dt_mc_20250902155652novm4",
    "timestamp": 1756973400,
    "datetime_utc": "2025-09-04T08:10:00+00:00",
    "tournament": "TI14国际邀请赛",
    "team1": "Aurora",
    "team2": "XG",
    "best_type": "BO3",
    "status": "进行中",
    "result": "0-0",
    "status_code": "1",
    "api_status": 1,
    "tournament_id": "dt_tt_20250524123429r04um",
    "game_type": "Dota 2",
    "grade": "S级",
    "star": "2",
    "bo": "",
    "map_info": "",
    "round_name": "",
    "stage_desc": "小组赛",
    "team1_logo": "https://oss.5eplay.com/cloudx/p/sport/dota2/team/claqolkconkqks63chtg.png",
    "team2_logo": "https://oss.5eplay.com/cloudx/p/sport/dota2/team/cqjmgd4conkotam7vtag.png",
    "tournament_logo": "https://oss.5eplay.com/cloudx/p/sport/dota2/tournament/cnmju9cconklgsjvgm8g.png"
  },
  {
    "id": "dt_mc_20250902155652qf4ks",
    "timestamp": 1756983600,
    "datetime_utc": "2025-09-04T11:00:00+00:00",
    "tournament": "TI14国际邀请赛",
    "team1": "PARI",
    "team2": "Heroic",
    "best_type": "BO3",
    "status": "未开始",
    "result": "0-0",
    "status_code": "0",
    "api_status": 1,
    "tournament_id": "dt_tt_20250524123429r04um",
    "game_type": "Dota 2",
    "grade": "S级",
    "star": "1",
    "bo": "",
    "map_info": "",
    "round_name": "",
    "stage_desc": "小组赛",
    "team1_logo": "https://oss.5eplay.com/cloudx/p/sport/dota2/team/cs8ksbkconkotam8181g.png",
    "team2_logo": "https://oss.5eplay.com/cloudx/p/sport/dota2/team/co51l8kconklgsjvh0pg.png",
    "tournament_logo": "https://oss.5eplay.com/cloudx/p/sport/dota2/tournament/cnmju9cconklgsjvgm8g.png"
  },
  {
    "id": "dt_mc_20250902155653x3ts1",
    "timestamp": 1756983600,
    "datetime_utc": "2025-09-04T11:00:00+00:00",
    "tournament": "TI14国际邀请赛",
    "team1": "BB",
    "team2": "NGX",
    "best_type": "BO3",
    "status": "未开始",
    "result": "0-0",
    "status_code": "0",
    "api_status": 1,
    "tournament_id": "dt_tt_20250524123429r04um",
    "game_type": "Dota 2",
    "grade": "S级",
    "star": "1",
    "bo": "",
    "map_info": "",
    "round_name": "",
    "stage_desc": "小组赛",
    "team1_logo": "https://oss.5eplay.com/cloudx/p/sport/dota2/team/merge_cq17d4sconkotam7vf30.png",
    "team2_logo": "https://oss.5eplay.com/sport/dota2/team/cf42dhf4nfq15265j85g.png",
    "tournament_logo": "https://oss.5eplay.com/cloudx/p/sport/dota2/tournament/cnmju9cconklgsjvgm8g.png"
  },
  {
    "id": "dt_mc_202509021556532qz85",
    "timestamp": 1756983600,
    "datetime_utc": "2025-09-04T11:00:00+00:00",
    "tournament": "TI14国际邀请赛",
    "team1": "Tidebd",
    "team2": "NaVi",
    "best_type": "BO3",
    "status": "未开始",
    "result": "0-0",
    "status_code": "0",
    "api_status": 1,
    "tournament_id": "dt_tt_20250524123429r04um",
    "game_type": "Dota 2",
    "grade": "S级",
    "star": "2",
    "bo": "",
    "map_info": "",
    "round_name": "",
    "stage_desc": "小组赛",
    "team1_logo": "https://oss.5eplay.com/cloudx/p/sport/dota2/team/d1iduu4conkt3legeq30.png",
    "team2_logo": "https://oss.5eplay.com/sport/dota2/team/ce422474nfq4l7bsk4mg.png",
    "tournament_logo": "https://oss.5eplay.com/cloudx/p/sport/dota2/tournament/cnmju9cconklgsjvgm8g.png"
  },
  {
    "id": "dt_mc_20250902155954e5hdi",
    "timestamp": 1756983600,
    "datetime_utc": "2025-09-04T11:00:00+00:00",
    "tournament": "TI14国际邀请赛",
    "team1": "Liquid",
    "team2": "BOOM",
    "best_type": "BO3",
    "status": "未开始",
    "result": "0-0",
    "status_code": "0",
    "api_status": 1,
    "tournament_id": "dt_tt_20250524123429r04um",
    "game_type": "Dota 2",
    "grade": "S级",
    "star": "1",
    "bo": "",
    "map_info": "",
    "round_name": "",
    "stage_desc": "小组赛",
    "team1_logo": "https://oss.5eplay.com/cloudx/p/sport/dota2/team/cgv00pv4nfqe2nie42mg.png",
    "team2_logo": "https://oss.5eplay.com/sport/dota2/team/merge_cfrftapll806h1bg26o0.png",
    "tournament_logo": "https://oss.5eplay.com/cloudx/p/sport/dota2/tournament/cnmju9cconklgsjvgm8g.png"
  },
  {
    "id": "dt_mc_20250902155654q3xij",
    "timestamp": 1756994400,
    "datetime_utc": "2025-09-04T14:00:00+00:00",
    "tournament": "TI14国际邀请赛",
    "team1": "TBD",
    "team2": "TBD",
    "best_type": "BO3",
    "status": "未开始",
    "result": "0-0",
    "status_code": "0",
    "api_status": 1,
    "tournament_id": "dt_tt_20250524123429r04um",
    "game_type": "Dota 2",
    "grade": "S级",
    "star": "",
    "bo": "",
    "map_info": "",
    "round_name": "",
    "stage_desc": "小组赛",
    "team1_logo": "https://oss.5eplay.com/sport/dota2/team/merge_cgengthll806h1bg2r80.png",
    "team2_logo": "https://oss.5eplay.com/sport/dota2/team/merge_cgenh29ll806h1bg2rb0.png",
    "tournament_logo": "https://oss.5eplay.com/cloudx/p/sport/dota2/tournament/cnmju9cconklgsjvgm8g.png"
  },
  {
    "id": "dt_mc_202509021559555is81",
    "timestamp": 1756994400,
    "datetime_utc": "2025-09-04T14:00:00+00:00",
    "tournament": "TI14国际邀请赛",
    "team1": "TBD",
    "team2": "TBD",
    "best_type": "BO3",
    "status": "未开始",
    "result": "0-0",
    "status_code": "0",
    "api_status": 1,
    "tournament_id": "dt_tt_20250524123429r04um",
    "game_type": "Dota 2",
    "grade": "S级",
    "star": "",
    "bo": "",
    "map_info": "",
    "round_name": "",
    "stage_desc": "小组赛",
    "team1_logo": "https://oss.5eplay.com/sport/dota2/team/merge_cgengthll806h1bg2r80.png",
    "team2_logo": "https://oss.5eplay.com/sport/dota2/team/merge_cgenh29ll806h1bg2rb0.png",
    "tournament_logo": "https://oss.5eplay.com/cloudx/p/sport/dota2/tournament/cnmju9cconklgsjvgm8g.png"
  },
  {
    "id": "dt_mc_202509021559551t7ez",
    "timestamp": 1756994400,
    "datetime_utc": "2025-09-04T14:00:00+00:00",
    "tournament": "TI14国际邀请赛",
    "team1": "TBD",
    "team2": "TBD",
    "best_type": "BO3",
    "status": "未开始",
    "result": "0-0",
    "status_code": "0",
    "api_status": 1,
    "tournament_id": "dt_tt_20250524123429r04um",
    "game_type": "Dota 2",
    "grade": "S级",
    "star": "",
    "bo": "",
    "map_info": "",
    "round_name": "",
    "stage_desc": "小组赛",
    "team1_logo": "https://oss.5eplay.com/sport/dota2/team/merge_cgengthll806h1bg2r80.png",
    "team2_logo": "https://oss.5eplay.com/sport/dota2/team/merge_cgenh29ll806h1bg2rb0.png",
    "tournament_logo": "https://oss.5eplay.com/cloudx/p/sport/dota2/tournament/cnmju9cconklgsjvgm8g.png"
  },
  {
    "id": "dt_mc_202509021603027pucz",
    "timestamp": 1756994400,
    "datetime_utc": "2025-09-04T14:00:00+00:00",
    "tournament": "TI14国际邀请赛",
    "team1": "TBD",
    "team2": "TBD",
    "best_type": "BO3",
    "status": "未开始",
    "result": "0-0",
    "status_code": "0",
    "api_status": 1,
    "tournament_id": "dt_tt_20250524123429r04um",
    "game_type": "Dota 2",
    "grade": "S级",
    "star": "",
    "bo": "",
    "map_info": "",
    "round_name": "",
    "stage_desc": "小组赛",
    "team1_logo": "https://oss.5eplay.com/sport/dota2/team/merge_cgengthll806h1bg2r80.png",
    "team2_logo": "https://oss.5eplay.com/sport/dota2/team/merge_cgenh29ll806h1bg2rb0.png",
    "tournament_logo": "https://oss.5eplay.com/cloudx/p/sport/dota2/tournament/cnmju9cconklgsjvgm8g.png"
  },
  {
    "id": "dt_mc_20250902155955y6ibv",
    "timestamp": 1757005200,
    "datetime_utc": "2025-09-04T17:00:00+00:00",
    "tournament": "TI14国际邀请赛",
    "team1": "TBD",
    "team2": "TBD",
    "best_type": "BO3",
    "status": "未开始",
    "result": "0-0",
    "status_code": "0",
    "api_status": 1,
    "tournament_id": "dt_tt_20250524123429r04um",
    "game_type": "Dota 2",
    "grade": "S级",
    "star": "",
    "bo": "",
    "map_info": "",
    "round_name": "",
    "stage_desc": "小组赛",
    "team1_logo": "https://oss.5eplay.com/sport/dota2/team/merge_cgengthll806h1bg2r80.png",
    "team2_logo": "https://oss.5eplay.com/sport/dota2/team/merge_cgenh29ll806h1bg2rb0.png",
    "tournament_logo": "https://oss.5eplay.com/cloudx/p/sport/dota2/tournament/cnmju9cconklgsjvgm8g.png"
  },
  {
    "id": "dt_mc_20250902155956ztefx",
    "timestamp": 1757005200,
    "datetime_utc": "2025-09-04T17:00:00+00:00",
    "tournament": "TI14国际邀请赛",
    "team1": "TBD",
    "team2": "TBD",
    "best_type": "BO3",
    "status": "未开始",
    "result": "0-0",
    "status_code": "0",
    "api_status": 1,
    "tournament_id": "dt_tt_20250524123429r04um",
    "game_type": "Dota 2",
    "grade": "S级",
    "star": "",
    "bo": "",
    "map_info": "",
    "round_name": "",
    "stage_desc": "小组赛",
    "team1_logo": "https://oss.5eplay.com/sport/dota2/team/merge_cgengthll806h1bg2r80.png",
    "team2_logo": "https://oss.5eplay.com/sport/dota2/team/merge_cgenh29ll806h1bg2rb0.png",
    "tournament_logo": "https://oss.5eplay.com/cloudx/p/sport/dota2/tournament/cnmju9cconklgsjvgm8g.png"
  },
  {
    "id": "dt_mc_202509021602596s76p",
    "timestamp": 1757005200,
    "datetime_utc": "2025-09-04T17:00:00+00:00",
    "tournament": "TI14国际邀请赛",
    "team1": "TBD",
    "team2": "TBD",
    "best_type": "BO3",
    "status": "未开始",
    "result": "0-0",
    "status_code": "0",
    "api_status": 1,
    "tournament_id": "dt_tt_20250524123429r04um",
    "game_type": "Dota 2",
    "grade": "S级",
    "star": "",
    "bo": "",
    "map_info": "",
    "round_name": "",
    "stage_desc": "小组赛",
    "team1_logo": "https://oss.5eplay.com/sport/dota2/team/merge_cgengthll806h1bg2r80.png",
    "team2_logo": "https://oss.5eplay.com/sport/dota2/team/merge_cgenh29ll806h1bg2rb0.png",
    "tournament_logo": "https://oss.5eplay.com/cloudx/p/sport/dota2/tournament/cnmju9cconklgsjvgm8g.png"
  },
  {
    "id": "dt_mc_20250902160259sls4y",
    "timestamp": 1757005200,
    "datetime_utc": "2025-09-04T17:00:00+00:00",
    "tournament": "TI14国际邀请赛",
    "team1": "TBD",
    "team2": "TBD",
    "best_type": "BO3",
    "status": "未开始",
    "result": "0-0",
    "status_code": "0",
    "api_status": 1,
    "tournament_id": "dt_tt_20250524123429r04um",
    "game_type": "Dota 2",
    "grade": "S级",
    "star": "",
    "bo": "",
    "map_info": "",
    "round_name": "",
    "stage_desc": "小组赛",
    "team1_logo": "https://oss.5eplay.com/sport/dota2/team/merge_cgengthll806h1bg2r80.png",
    "team2_logo": "https://oss.5eplay.com/sport/dota2/team/merge_cgenh29ll806h1bg2rb0.png",
    "tournament_logo": "https://oss.5eplay.com/cloudx/p/sport/dota2/tournament/cnmju9cconklgsjvgm8g.png"
  },
  {
    "id": "dt_mc_20250901235355x8lm2",
    "timestamp": 1757008800,
    "datetime_utc": "2025-09-04T18:00:00+00:00",
    "tournament": "ACS 系列赛 2",
    "team1": "HunterZ",
    "team2": "Lava",
    "best_type": "BO3",
    "status": "未开始",
    "result": "0-0",
    "status_code": "0",
    "api_status": 1,
    "tournament_id": "dt_tt_20250901235351dhf4h",
    "game_type": "Dota 2",
    "grade": "",
    "star": "",
    "bo": "",
    "map_info": "",
    "round_name": "",
    "stage_desc": "小组赛",
    "team1_logo": "https://oss.5eplay.com/cloudx/p/sport/dota2/team/d2qsm6sconkqbk3bnm20.png",
    "team2_logo": "https://oss.5eplay.com/sport/dota2/team/cf0bh3f4nfq15265j7h0.png",
    "tournament_logo": "https://oss.5eplay.com/cloudx/p/sport/dota2/tournament/d2297isconkt3legeu1g.png"
  },
  {
    "id": "dt_mc_20250901235356mkesl",
    "timestamp": 1757019600,
    "datetime_utc": "2025-09-04T21:00:00+00:00",
    "tournament": "ACS 系列赛 2",
    "team1": "EB",
    "team2": "TC",
    "best_type": "BO3",
    "status": "未开始",
    "result": "0-0",
    "status_code": "0",
    "api_status": 1,
    "tournament_id": "dt_tt_20250901235351dhf4h",
    "game_type": "Dota 2",
    "grade": "",
    "star": "",
    "bo": "",
    "map_info": "",
    "round_name": "",
    "stage_desc": "小组赛",
    "team1_logo": "https://oss.5eplay.com/cloudx/p/sport/dota2/team/cm1c8ksconkqks63d3kg.png",
    "team2_logo": "https://oss.5eplay.com/cloudx/p/sport/dota2/team/cuhf0bkconkqmjpn82fg.png",
    "tournament_logo": "https://oss.5eplay.com/cloudx/p/sport/dota2/tournament/d2297isconkt3legeu1g.png"
  },
  {
    "id": "dt_mc_20250902164451aqah3",
    "timestamp": 1757059200,
    "datetime_utc": "2025-09-05T08:00:00+00:00",
    "tournament": "TI14国际邀请赛",
    "team1": "TBD",
    "team2": "TBD",
    "best_type": "BO3",
    "status": "未开始",
    "result": "0-0",
    "status_code": "0",
    "api_status": 1,
    "tournament_id": "dt_tt_20250524123429r04um",
    "game_type": "Dota 2",
    "grade": "S级",
    "star": "",
    "bo": "",
    "map_info": "",
    "round_name": "",
    "stage_desc": "小组赛",
    "team1_logo": "https://oss.5eplay.com/sport/dota2/team/merge_cgengthll806h1bg2r80.png",
    "team2_logo": "https://oss.5eplay.com/sport/dota2/team/merge_cgenh29ll806h1bg2rb0.png",
    "tournament_logo": "https://oss.5eplay.com/cloudx/p/sport/dota2/tournament/cnmju9cconklgsjvgm8g.png"
  },
  {
    "id": "dt_mc_20250902164452qlupl",
    "timestamp": 1757059200,
    "datetime_utc": "2025-09-05T08:00:00+00:00",
    "tournament": "TI14国际邀请赛",
    "team1": "TBD",
    "team2": "TBD",
    "best_type": "BO3",
    "status": "未开始",
    "result": "0-0",
    "status_code": "0",
    "api_status": 1,
    "tournament_id": "dt_tt_20250524123429r04um",
    "game_type": "Dota 2",
    "grade": "S级",
    "star": "",
    "bo": "",
    "map_info": "",
    "round_name": "",
    "stage_desc": "小组赛",
    "team1_logo": "https://oss.5eplay.com/sport/dota2/team/merge_cgengthll806h1bg2r80.png",
    "team2_logo": "https://oss.5eplay.com/sport/dota2/team/merge_cgenh29ll806h1bg2rb0.png",
    "tournament_logo": "https://oss.5eplay.com/cloudx/p/sport/dota2/tournament/cnmju9cconklgsjvgm8g.png"
  },
  {
    "id": "dt_mc_20250902164453j8v4z",
    "timestamp": 1757059200,
    "datetime_utc": "2025-09-05T08:00:00+00:00",
    "tournament": "TI14国际邀请赛",
    "team1": "TBD",
    "team2": "TBD",
    "best_type": "BO3",
    "status": "未开始",
    "result": "0-0",
    "status_code": "0",
    "api_status": 1,
    "tournament_id": "dt_tt_20250524123429r04um",
    "game_type": "Dota 2",
    "grade": "S级",
    "star": "",
    "bo": "",
    "map_info": "",
    "round_name": "",
    "stage_desc": "小组赛",
    "team1_logo": "https://oss.5eplay.com/sport/dota2/team/merge_cgengthll806h1bg2r80.png",
    "team2_logo": "https://oss.5eplay.com/sport/dota2/team/merge_cgenh29ll806h1bg2rb0.png",
    "tournament_logo": "https://oss.5eplay.com/cloudx/p/sport/dota2/tournament/cnmju9cconklgsjvgm8g.png"
  },
  {
    "id": "dt_mc_202509021702533lruo",
    "timestamp": 1757059200,
    "datetime_utc": "2025-09-05T08:00:00+00:00",
    "tournament": "TI14国际邀请赛",
    "team1": "TBD",
    "team2": "TBD",
    "best_type": "BO3",
    "status": "未开始",
    "result": "0-0",
    "status_code": "0",
    "api_status": 1,
    "tournament_id": "dt_tt_20250524123429r04um",
    "game_type": "Dota 2",
    "grade": "S级",
    "star": "",
    "bo": "",
    "map_info": "",
    "round_name": "",
    "stage_desc": "小组赛",
    "team1_logo": "https://oss.5eplay.com/sport/dota2/team/merge_cgengthll806h1bg2r80.png",
    "team2_logo": "https://oss.5eplay.com/sport/dota2/team/merge_cgenh29ll806h1bg2rb0.png",
    "tournament_logo": "https://oss.5eplay.com/cloudx/p/sport/dota2/tournament/cnmju9cconklgsjvgm8g.png"
  },
  {
    "id": "dt_mc_20250902164453j9hbp",
    "timestamp": 1757070000,
    "datetime_utc": "2025-09-05T11:00:00+00:00",
    "tournament": "TI14国际邀请赛",
    "team1": "TBD",
    "team2": "TBD",
    "best_type": "BO3",
    "status": "未开始",
    "result": "0-0",
    "status_code": "0",
    "api_status": 1,
    "tournament_id": "dt_tt_20250524123429r04um",
    "game_type": "Dota 2",
    "grade": "S级",
    "star": "",
    "bo": "",
    "map_info": "",
    "round_name": "",
    "stage_desc": "小组赛",
    "team1_logo": "https://oss.5eplay.com/sport/dota2/team/merge_cgengthll806h1bg2r80.png",
    "team2_logo": "https://oss.5eplay.com/sport/dota2/team/merge_cgenh29ll806h1bg2rb0.png",
    "tournament_logo": "https://oss.5eplay.com/cloudx/p/sport/dota2/tournament/cnmju9cconklgsjvgm8g.png"
  },
  {
    "id": "dt_mc_20250902164454bc9gn",
    "timestamp": 1757070000,
    "datetime_utc": "2025-09-05T11:00:00+00:00",
    "tournament": "TI14国际邀请赛",
    "team1": "TBD",
    "team2": "TBD",
    "best_type": "BO3",
    "status": "未开始",
    "result": "0-0",
    "status_code": "0",
    "api_status": 1,
    "tournament_id": "dt_tt_20250524123429r04um",
    "game_type": "Dota 2",
    "grade": "S级",
    "star": "",
    "bo": "",
    "map_info": "",
    "round_name": "",
    "stage_desc": "小组赛",
    "team1_logo": "https://oss.5eplay.com/sport/dota2/team/merge_cgengthll806h1bg2r80.png",
    "team2_logo": "https://oss.5eplay.com/sport/dota2/team/merge_cgenh29ll806h1bg2rb0.png",
    "tournament_logo": "https://oss.5eplay.com/cloudx/p/sport/dota2/tournament/cnmju9cconklgsjvgm8g.png"
  },
  {
    "id": "dt_mc_202509021644553xm64",
    "timestamp": 1757070000,
    "datetime_utc": "2025-09-05T11:00:00+00:00",
    "tournament": "TI14国际邀请赛",
    "team1": "TBD",
    "team2": "TBD",
    "best_type": "BO3",
    "status": "未开始",
    "result": "0-0",
    "status_code": "0",
    "api_status": 1,
    "tournament_id": "dt_tt_20250524123429r04um",
    "game_type": "Dota 2",
    "grade": "S级",
    "star": "",
    "bo": "",
    "map_info": "",
    "round_name": "",
    "stage_desc": "小组赛",
    "team1_logo": "https://oss.5eplay.com/sport/dota2/team/merge_cgengthll806h1bg2r80.png",
    "team2_logo": "https://oss.5eplay.com/sport/dota2/team/merge_cgenh29ll806h1bg2rb0.png",
    "tournament_logo": "https://oss.5eplay.com/cloudx/p/sport/dota2/tournament/cnmju9cconklgsjvgm8g.png"
  },
  {
    "id": "dt_mc_20250902164455m28ex",
    "timestamp": 1757070000,
    "datetime_utc": "2025-09-05T11:00:00+00:00",
    "tournament": "TI14国际邀请赛",
    "team1": "TBD",
    "team2": "TBD",
    "best_type": "BO3",
    "status": "未开始",
    "result": "0-0",
    "status_code": "0",
    "api_status": 1,
    "tournament_id": "dt_tt_20250524123429r04um",
    "game_type": "Dota 2",
    "grade": "S级",
    "star": "",
    "bo": "",
    "map_info": "",
    "round_name": "",
    "stage_desc": "小组赛",
    "team1_logo": "https://oss.5eplay.com/sport/dota2/team/merge_cgengthll806h1bg2r80.png",
    "team2_logo": "https://oss.5eplay.com/sport/dota2/team/merge_cgenh29ll806h1bg2rb0.png",
    "tournament_logo": "https://oss.5eplay.com/cloudx/p/sport/dota2/tournament/cnmju9cconklgsjvgm8g.png"
  },
  {
    "id": "dt_mc_20250902164752ztfzw",
    "timestamp": 1757080800,
    "datetime_utc": "2025-09-05T14:00:00+00:00",
    "tournament": "TI14国际邀请赛",
    "team1": "TBD",
    "team2": "TBD",
    "best_type": "BO3",
    "status": "未开始",
    "result": "0-0",
    "status_code": "0",
    "api_status": 1,
    "tournament_id": "dt_tt_20250524123429r04um",
    "game_type": "Dota 2",
    "grade": "S级",
    "star": "",
    "bo": "",
    "map_info": "",
    "round_name": "",
    "stage_desc": "小组赛",
    "team1_logo": "https://oss.5eplay.com/sport/dota2/team/merge_cgengthll806h1bg2r80.png",
    "team2_logo": "https://oss.5eplay.com/sport/dota2/team/merge_cgenh29ll806h1bg2rb0.png",
    "tournament_logo": "https://oss.5eplay.com/cloudx/p/sport/dota2/tournament/cnmju9cconklgsjvgm8g.png"
  },
  {
    "id": "dt_mc_20250902164753q8dec",
    "timestamp": 1757080800,
    "datetime_utc": "2025-09-05T14:00:00+00:00",
    "tournament": "TI14国际邀请赛",
    "team1": "TBD",
    "team2": "TBD",
    "best_type": "BO3",
    "status": "未开始",
    "result": "0-0",
    "status_code": "0",
    "api_status": 1,
    "tournament_id": "dt_tt_20250524123429r04um",
    "game_type": "Dota 2",
    "grade": "S级",
    "star": "",
    "bo": "",
    "map_info": "",
    "round_name": "",
    "stage_desc": "小组赛",
    "team1_logo": "https://oss.5eplay.com/sport/dota2/team/merge_cgengthll806h1bg2r80.png",
    "team2_logo": "https://oss.5eplay.com/sport/dota2/team/merge_cgenh29ll806h1bg2rb0.png",
    "tournament_logo": "https://oss.5eplay.com/cloudx/p/sport/dota2/tournament/cnmju9cconklgsjvgm8g.png"
  },
  {
    "id": "dt_mc_2025090216595248h62",
    "timestamp": 1757080800,
    "datetime_utc": "2025-09-05T14:00:00+00:00",
    "tournament": "TI14国际邀请赛",
    "team1": "TBD",
    "team2": "TBD",
    "best_type": "BO3",
    "status": "未开始",
    "result": "0-0",
    "status_code": "0",
    "api_status": 1,
    "tournament_id": "dt_tt_20250524123429r04um",
    "game_type": "Dota 2",
    "grade": "S级",
    "star": "",
    "bo": "",
    "map_info": "",
    "round_name": "",
    "stage_desc": "小组赛",
    "team1_logo": "https://oss.5eplay.com/sport/dota2/team/merge_cgengthll806h1bg2r80.png",
    "team2_logo": "https://oss.5eplay.com/sport/dota2/team/merge_cgenh29ll806h1bg2rb0.png",
    "tournament_logo": "https://oss.5eplay.com/cloudx/p/sport/dota2/tournament/cnmju9cconklgsjvgm8g.png"
  },
  {
    "id": "dt_mc_202509021702537dj27",
    "timestamp": 1757080800,
    "datetime_utc": "2025-09-05T14:00:00+00:00",
    "tournament": "TI14国际邀请赛",
    "team1": "TBD",
    "team2": "TBD",
    "best_type": "BO3",
    "status": "未开始",
    "result": "0-0",
    "status_code": "0",
    "api_status": 1,
    "tournament_id": "dt_tt_20250524123429r04um",
    "game_type": "Dota 2",
    "grade": "S级",
    "star": "",
    "bo": "",
    "map_info": "",
    "round_name": "",
    "stage_desc": "小组赛",
    "team1_logo": "https://oss.5eplay.com/sport/dota2/team/merge_cgengthll806h1bg2r80.png",
    "team2_logo": "https://oss.5eplay.com/sport/dota2/team/merge_cgenh29ll806h1bg2rb0.png",
    "tournament_logo": "https://oss.5eplay.com/cloudx/p/sport/dota2/tournament/cnmju9cconklgsjvgm8g.png"
  },
  {
    "id": "dt_mc_202509021647531a02y",
    "timestamp": 1757145600,
    "datetime_utc": "2025-09-06T08:00:00+00:00",
    "tournament": "TI14国际邀请赛",
    "team1": "TBD",
    "team2": "TBD",
    "best_type": "BO3",
    "status": "未开始",
    "result": "0-0",
    "status_code": "0",
    "api_status": 1,
    "tournament_id": "dt_tt_20250524123429r04um",
    "game_type": "Dota 2",
    "grade": "S级",
    "star": "",
    "bo": "",
    "map_info": "",
    "round_name": "",
    "stage_desc": "小组赛",
    "team1_logo": "https://oss.5eplay.com/sport/dota2/team/merge_cgengthll806h1bg2r80.png",
    "team2_logo": "https://oss.5eplay.com/sport/dota2/team/merge_cgenh29ll806h1bg2rb0.png",
    "tournament_logo": "https://oss.5eplay.com/cloudx/p/sport/dota2/tournament/cnmju9cconklgsjvgm8g.png"
  },
  {
    "id": "dt_mc_202509021647544krlf",
    "timestamp": 1757145600,
    "datetime_utc": "2025-09-06T08:00:00+00:00",
    "tournament": "TI14国际邀请赛",
    "team1": "TBD",
    "team2": "TBD",
    "best_type": "BO3",
    "status": "未开始",
    "result": "0-0",
    "status_code": "0",
    "api_status": 1,
    "tournament_id": "dt_tt_20250524123429r04um",
    "game_type": "Dota 2",
    "grade": "S级",
    "star": "",
    "bo": "",
    "map_info": "",
    "round_name": "",
    "stage_desc": "小组赛",
    "team1_logo": "https://oss.5eplay.com/sport/dota2/team/merge_cgengthll806h1bg2r80.png",
    "team2_logo": "https://oss.5eplay.com/sport/dota2/team/merge_cgenh29ll806h1bg2rb0.png",
    "tournament_logo": "https://oss.5eplay.com/cloudx/p/sport/dota2/tournament/cnmju9cconklgsjvgm8g.png"
  },
  {
    "id": "dt_mc_20250902164755k9i7s",
    "timestamp": 1757145600,
    "datetime_utc": "2025-09-06T08:00:00+00:00",
    "tournament": "TI14国际邀请赛",
    "team1": "TBD",
    "team2": "TBD",
    "best_type": "BO3",
    "status": "未开始",
    "result": "0-0",
    "status_code": "0",
    "api_status": 1,
    "tournament_id": "dt_tt_20250524123429r04um",
    "game_type": "Dota 2",
    "grade": "S级",
    "star": "",
    "bo": "",
    "map_info": "",
    "round_name": "",
    "stage_desc": "小组赛",
    "team1_logo": "https://oss.5eplay.com/sport/dota2/team/merge_cgengthll806h1bg2r80.png",
    "team2_logo": "https://oss.5eplay.com/sport/dota2/team/merge_cgenh29ll806h1bg2rb0.png",
    "tournament_logo": "https://oss.5eplay.com/cloudx/p/sport/dota2/tournament/cnmju9cconklgsjvgm8g.png"
  },
  {
    "id": "dt_mc_20250902170254tm0n6",
    "timestamp": 1757145600,
    "datetime_utc": "2025-09-06T08:00:00+00:00",
    "tournament": "TI14国际邀请赛",
    "team1": "TBD",
    "team2": "TBD",
    "best_type": "BO3",
    "status": "未开始",
    "result": "0-0",
    "status_code": "0",
    "api_status": 1,
    "tournament_id": "dt_tt_20250524123429r04um",
    "game_type": "Dota 2",
    "grade": "S级",
    "star": "",
    "bo": "",
    "map_info": "",
    "round_name": "",
    "stage_desc": "小组赛",
    "team1_logo": "https://oss.5eplay.com/sport/dota2/team/merge_cgengthll806h1bg2r80.png",
    "team2_logo": "https://oss.5eplay.com/sport/dota2/team/merge_cgenh29ll806h1bg2rb0.png",
    "tournament_logo": "https://oss.5eplay.com/cloudx/p/sport/dota2/tournament/cnmju9cconklgsjvgm8g.png"
  },
  {
    "id": "dt_mc_20250902164755ngfti",
    "timestamp": 1757156400,
    "datetime_utc": "2025-09-06T11:00:00+00:00",
    "tournament": "TI14国际邀请赛",
    "team1": "TBD",
    "team2": "TBD",
    "best_type": "BO3",
    "status": "未开始",
    "result": "0-0",
    "status_code": "0",
    "api_status": 1,
    "tournament_id": "dt_tt_20250524123429r04um",
    "game_type": "Dota 2",
    "grade": "S级",
    "star": "",
    "bo": "",
    "map_info": "",
    "round_name": "",
    "stage_desc": "小组赛",
    "team1_logo": "https://oss.5eplay.com/sport/dota2/team/merge_cgengthll806h1bg2r80.png",
    "team2_logo": "https://oss.5eplay.com/sport/dota2/team/merge_cgenh29ll806h1bg2rb0.png",
    "tournament_logo": "https://oss.5eplay.com/cloudx/p/sport/dota2/tournament/cnmju9cconklgsjvgm8g.png"
  },
  {
    "id": "dt_mc_20250902164756urrot",
    "timestamp": 1757156400,
    "datetime_utc": "2025-09-06T11:00:00+00:00",
    "tournament": "TI14国际邀请赛",
    "team1": "TBD",
    "team2": "TBD",
    "best_type": "BO3",
    "status": "未开始",
    "result": "0-0",
    "status_code": "0",
    "api_status": 1,
    "tournament_id": "dt_tt_20250524123429r04um",
    "game_type": "Dota 2",
    "grade": "S级",
    "star": "",
    "bo": "",
    "map_info": "",
    "round_name": "",
    "stage_desc": "小组赛",
    "team1_logo": "https://oss.5eplay.com/sport/dota2/team/merge_cgengthll806h1bg2r80.png",
    "team2_logo": "https://oss.5eplay.com/sport/dota2/team/merge_cgenh29ll806h1bg2rb0.png",
    "tournament_logo": "https://oss.5eplay.com/cloudx/p/sport/dota2/tournament/cnmju9cconklgsjvgm8g.png"
  },
  {
    "id": "dt_mc_20250902164756ocbf3",
    "timestamp": 1757156400,
    "datetime_utc": "2025-09-06T11:00:00+00:00",
    "tournament": "TI14国际邀请赛",
    "team1": "TBD",
    "team2": "TBD",
    "best_type": "BO3",
    "status": "未开始",
    "result": "0-0",
    "status_code": "0",
    "api_status": 1,
    "tournament_id": "dt_tt_20250524123429r04um",
    "game_type": "Dota 2",
    "grade": "S级",
    "star": "",
    "bo": "",
    "map_info": "",
    "round_name": "",
    "stage_desc": "小组赛",
    "team1_logo": "https://oss.5eplay.com/sport/dota2/team/merge_cgengthll806h1bg2r80.png",
    "team2_logo": "https://oss.5eplay.com/sport/dota2/team/merge_cgenh29ll806h1bg2rb0.png",
    "tournament_logo": "https://oss.5eplay.com/cloudx/p/sport/dota2/tournament/cnmju9cconklgsjvgm8g.png"
  },
  {
    "id": "dt_mc_20250902164757oxke3",
    "timestamp": 1757156400,
    "datetime_utc": "2025-09-06T11:00:00+00:00",
    "tournament": "TI14国际邀请赛",
    "team1": "TBD",
    "team2": "TBD",
    "best_type": "BO3",
    "status": "未开始",
    "result": "0-0",
    "status_code": "0",
    "api_status": 1,
    "tournament_id": "dt_tt_20250524123429r04um",
    "game_type": "Dota 2",
    "grade": "S级",
    "star": "",
    "bo": "",
    "map_info": "",
    "round_name": "",
    "stage_desc": "小组赛",
    "team1_logo": "https://oss.5eplay.com/sport/dota2/team/merge_cgengthll806h1bg2r80.png",
    "team2_logo": "https://oss.5eplay.com/sport/dota2/team/merge_cgenh29ll806h1bg2rb0.png",
    "tournament_logo": "https://oss.5eplay.com/cloudx/p/sport/dota2/tournament/cnmju9cconklgsjvgm8g.png"
  },
  {
    "id": "dt_mc_2025090216475741zp3",
    "timestamp": 1757167200,
    "datetime_utc": "2025-09-06T14:00:00+00:00",
    "tournament": "TI14国际邀请赛",
    "team1": "TBD",
    "team2": "TBD",
    "best_type": "BO3",
    "status": "未开始",
    "result": "0-0",
    "status_code": "0",
    "api_status": 1,
    "tournament_id": "dt_tt_20250524123429r04um",
    "game_type": "Dota 2",
    "grade": "S级",
    "star": "",
    "bo": "",
    "map_info": "",
    "round_name": "",
    "stage_desc": "小组赛",
    "team1_logo": "https://oss.5eplay.com/sport/dota2/team/merge_cgengthll806h1bg2r80.png",
    "team2_logo": "https://oss.5eplay.com/sport/dota2/team/merge_cgenh29ll806h1bg2rb0.png",
    "tournament_logo": "https://oss.5eplay.com/cloudx/p/sport/dota2/tournament/cnmju9cconklgsjvgm8g.png"
  },
  {
    "id": "dt_mc_20250902164758euqmq",
    "timestamp": 1757167200,
    "datetime_utc": "2025-09-06T14:00:00+00:00",
    "tournament": "TI14国际邀请赛",
    "team1": "TBD",
    "team2": "TBD",
    "best_type": "BO3",
    "status": "未开始",
    "result": "0-0",
    "status_code": "0",
    "api_status": 1,
    "tournament_id": "dt_tt_20250524123429r04um",
    "game_type": "Dota 2",
    "grade": "S级",
    "star": "",
    "bo": "",
    "map_info": "",
    "round_name": "",
    "stage_desc": "小组赛",
    "team1_logo": "https://oss.5eplay.com/sport/dota2/team/merge_cgengthll806h1bg2r80.png",
    "team2_logo": "https://oss.5eplay.com/sport/dota2/team/merge_cgenh29ll806h1bg2rb0.png",
    "tournament_logo": "https://oss.5eplay.com/cloudx/p/sport/dota2/tournament/cnmju9cconklgsjvgm8g.png"
  }
]