[
  {
    "id": "csgo_mc_2385581",
    "start_timestamp": 1757800800,
    "end_timestamp": 0,
    "start_datetime_utc": "2025-09-13T22:00:00+00:00",
    "end_datetime_utc": "2025-09-14T00:30:00+00:00",
    "tournament": "PrizePicks 北美复兴杯 S9",
    "team1": "BOSS",
    "team2": "LAG",
    "best_type": "BO3",
    "status": "已结束",
    "result": "2-0",
    "status_code": "2",
    "api_status": 2,
    "tournament_id": "csgo_tt_8697",
    "game_type": "CS:GO",
    "grade": "其他",
    "star": "0",
    "bo": "",
    "map_info": "",
    "round_name": "1/4决赛",
    "stage_desc": "淘汰赛 1/4决赛",
    "tournament_stage": "淘汰赛 1/4决赛",
    "team1_logo": "https://oss.5eplay.com/cloudx/p/sport/csgo/team/cnhsrdkconkqks63ecag.png",
    "team2_logo": "https://oss.5eplay.com/cloudx/p/sport/csgo/team/merge_clp62lsconkqks63csb0.png",
    "tournament_logo": "https://oss.5eplay.com/cloudx/p/sport/csgo/tournament/d07ja74conkt3lege6ug.png",
    "estimated_duration": 2.5
  },
  {
    "id": "csgo_mc_2385591",
    "start_timestamp": 1757803200,
    "end_timestamp": 0,
    "start_datetime_utc": "2025-09-13T22:40:00+00:00",
    "end_datetime_utc": "2025-09-14T01:10:00+00:00",
    "tournament": " CCT 第3赛季 南美系列赛4",
    "team1": "RED Canids",
    "team2": "Keyd",
    "best_type": "BO3",
    "status": "已结束",
    "result": "2-1",
    "status_code": "2",
    "api_status": 2,
    "tournament_id": "csgo_tt_8681",
    "game_type": "CS:GO",
    "grade": "其他",
    "star": "0",
    "bo": "",
    "map_info": "",
    "round_name": "十六强",
    "stage_desc": "淘汰赛 十六强",
    "tournament_stage": "淘汰赛 十六强",
    "team1_logo": "https://oss.5eplay.com/sport/csgo/team/7176.png",
    "team2_logo": "https://oss.5eplay.com/cloudx/p/sport/csgo/team/d1eal1kconkt3legeov0.png",
    "tournament_logo": "https://oss.5eplay.com/cloudx/p/sport/csgo/tournament/d1vrbfcconkt3leget7g.png",
    "estimated_duration": 2.5
  },
  {
    "id": "csgo_mc_2385584",
    "start_timestamp": 1757805900,
    "end_timestamp": 0,
    "start_datetime_utc": "2025-09-13T23:25:00+00:00",
    "end_datetime_utc": "2025-09-14T01:55:00+00:00",
    "tournament": "PrizePicks 北美复兴杯 S9",
    "team1": "Marsborne",
    "team2": "Fisher College",
    "best_type": "BO3",
    "status": "已结束",
    "result": "2-0",
    "status_code": "2",
    "api_status": 2,
    "tournament_id": "csgo_tt_8697",
    "game_type": "CS:GO",
    "grade": "其他",
    "star": "0",
    "bo": "",
    "map_info": "",
    "round_name": "1/4决赛",
    "stage_desc": "淘汰赛 1/4决赛",
    "tournament_stage": "淘汰赛 1/4决赛",
    "team1_logo": "https://oss.5eplay.com/cloudx/p/sport/csgo/team/cujam3kconkqmjpn84g0.png",
    "team2_logo": "https://oss.5eplay.com/cloudx/p/sport/csgo/team/ct9qa2cconkqmjpn7ac0.png",
    "tournament_logo": "https://oss.5eplay.com/cloudx/p/sport/csgo/tournament/d07ja74conkt3lege6ug.png",
    "estimated_duration": 2.5
  },
  {
    "id": "csgo_mc_2385583",
    "start_timestamp": 1757811600,
    "end_timestamp": 0,
    "start_datetime_utc": "2025-09-14T01:00:00+00:00",
    "end_datetime_utc": "2025-09-14T03:30:00+00:00",
    "tournament": "PrizePicks 北美复兴杯 S9",
    "team1": "Getting Info",
    "team2": "InControl",
    "best_type": "BO3",
    "status": "已结束",
    "result": "2-0",
    "status_code": "2",
    "api_status": 2,
    "tournament_id": "csgo_tt_8697",
    "game_type": "CS:GO",
    "grade": "其他",
    "star": "0",
    "bo": "",
    "map_info": "",
    "round_name": "1/4决赛",
    "stage_desc": "淘汰赛 1/4决赛",
    "tournament_stage": "淘汰赛 1/4决赛",
    "team1_logo": "https://oss.5eplay.com/sport/csgo/team/null.png",
    "team2_logo": "https://oss.5eplay.com/cloudx/p/sport/csgo/team/cvmb6p4conkt3lege0vg.png",
    "tournament_logo": "https://oss.5eplay.com/cloudx/p/sport/csgo/tournament/d07ja74conkt3lege6ug.png",
    "estimated_duration": 2.5
  },
  {
    "id": "csgo_mc_2385476",
    "start_timestamp": 1757815200,
    "end_timestamp": 0,
    "start_datetime_utc": "2025-09-14T02:00:00+00:00",
    "end_datetime_utc": "2025-09-14T04:30:00+00:00",
    "tournament": "极限之地 2025 大洋洲 封闭预选",
    "team1": "Rooster",
    "team2": "Gz",
    "best_type": "BO3",
    "status": "已结束",
    "result": "2-0",
    "status_code": "2",
    "api_status": 2,
    "tournament_id": "csgo_tt_8693",
    "game_type": "CS:GO",
    "grade": "其他",
    "star": "0",
    "bo": "",
    "map_info": "",
    "round_name": "决赛",
    "stage_desc": "淘汰赛 败者组 决赛",
    "tournament_stage": "淘汰赛 败者组 决赛",
    "team1_logo": "https://oss.5eplay.com/sport/csgo/team/hz/cec3u2f4nfq43340vma0.png",
    "team2_logo": "https://oss.5eplay.com/sport/csgo/team/hz/cec3sh74nfq43340vdsg.png",
    "tournament_logo": "https://oss.5eplay.com/cloudx/p/sport/csgo/tournament/d30dl24conkqbk3bnnd0.png",
    "estimated_duration": 2.5
  },
  {
    "id": "csgo_mc_2385477",
    "start_timestamp": 1757826000,
    "end_timestamp": 0,
    "start_datetime_utc": "2025-09-14T05:00:00+00:00",
    "end_datetime_utc": "2025-09-14T07:30:00+00:00",
    "tournament": "极限之地 2025 大洋洲 封闭预选",
    "team1": "SemperFi",
    "team2": "Rooster",
    "best_type": "BO3",
    "status": "已结束",
    "result": "0-2",
    "status_code": "2",
    "api_status": 2,
    "tournament_id": "csgo_tt_8693",
    "game_type": "CS:GO",
    "grade": "其他",
    "star": "0",
    "bo": "",
    "map_info": "",
    "round_name": "",
    "stage_desc": "淘汰赛  ",
    "tournament_stage": "淘汰赛",
    "team1_logo": "https://oss.5eplay.com/cloudx/p/sport/csgo/team/cs127acconkotam8152g.png",
    "team2_logo": "https://oss.5eplay.com/sport/csgo/team/hz/cec3u2f4nfq43340vma0.png",
    "tournament_logo": "https://oss.5eplay.com/cloudx/p/sport/csgo/tournament/d30dl24conkqbk3bnnd0.png",
    "estimated_duration": 2.5
  },
  {
    "id": "csgo_mc_2385558",
    "start_timestamp": 1757830281,
    "end_timestamp": 0,
    "start_datetime_utc": "2025-09-14T06:11:21+00:00",
    "end_datetime_utc": "2025-09-14T08:41:21+00:00",
    "tournament": "CCT 第3赛季 欧洲系列赛 7 封闭预选赛",
    "team1": "Algo",
    "team2": "THE",
    "best_type": "BO3",
    "status": "已结束",
    "result": "0-1",
    "status_code": "2",
    "api_status": 2,
    "tournament_id": "csgo_tt_8695",
    "game_type": "CS:GO",
    "grade": "",
    "star": "0",
    "bo": "",
    "map_info": "",
    "round_name": "首轮",
    "stage_desc": "小组赛 败者组 首轮",
    "tournament_stage": "小组赛 败者组 首轮",
    "team1_logo": "https://oss.5eplay.com/cloudx/p/sport/csgo/team/d1bna5cconkt3legelrg.png",
    "team2_logo": "https://oss.5eplay.com/cloudx/p/sport/csgo/team/merge_cr7cl34conkotam80i70.png",
    "tournament_logo": "https://oss.5eplay.com/cloudx/p/sport/csgo/tournament/d0guuusconkt3legeagg.png",
    "estimated_duration": 2.5
  },
  {
    "id": "csgo_mc_2385657",
    "start_timestamp": 1757836800,
    "end_timestamp": 0,
    "start_datetime_utc": "2025-09-14T08:00:00+00:00",
    "end_datetime_utc": "2025-09-14T10:30:00+00:00",
    "tournament": "CS 亚洲邀请赛 2025 东亚 公开预选赛",
    "team1": "CW",
    "team2": "The Huns",
    "best_type": "BO3",
    "status": "已结束",
    "result": "1-2",
    "status_code": "2",
    "api_status": 2,
    "tournament_id": "csgo_tt_8707",
    "game_type": "CS:GO",
    "grade": "",
    "star": "0",
    "bo": "",
    "map_info": "",
    "round_name": "决赛",
    "stage_desc": "淘汰赛 决赛",
    "tournament_stage": "淘汰赛 决赛",
    "team1_logo": "https://oss.5eplay.com/cloudx/p/sport/csgo/team/coqf55sconklgsjvhde0.png",
    "team2_logo": "https://oss.5eplay.com/cloudx/p/sport/csgo/team/merge_cl30rpsconkqks63c75g.png",
    "tournament_logo": "https://oss.5eplay.com/cloudx/p/sport/csgo/tournament/ctlqo7kconkqmjpn7hmg.png",
    "estimated_duration": 2.5
  },
  {
    "id": "csgo_mc_2385527",
    "start_timestamp": 1757836800,
    "end_timestamp": 0,
    "start_datetime_utc": "2025-09-14T08:00:00+00:00",
    "end_datetime_utc": "2025-09-14T10:30:00+00:00",
    "tournament": "CCT 第3赛季 欧洲系列赛 6",
    "team1": "ZT",
    "team2": "Tricked",
    "best_type": "BO3",
    "status": "已结束",
    "result": "0-2",
    "status_code": "2",
    "api_status": 2,
    "tournament_id": "csgo_tt_8680",
    "game_type": "CS:GO",
    "grade": "C级",
    "star": "0",
    "bo": "",
    "map_info": "",
    "round_name": "第三轮",
    "stage_desc": "小组赛 第三轮",
    "tournament_stage": "小组赛 第三轮",
    "team1_logo": "https://oss.5eplay.com/cloudx/p/sport/csgo/team/merge_cokslpkconklgsjvhc0g.png",
    "team2_logo": "https://oss.5eplay.com/cloudx/p/sport/csgo/team/cuvau1kconkqmjpn8e90.png",
    "tournament_logo": "https://oss.5eplay.com/cloudx/p/sport/csgo/tournament/d0guuusconkt3legeagg.png",
    "estimated_duration": 2.5
  },
  {
    "id": "csgo_mc_2385457",
    "start_timestamp": 1757836800,
    "end_timestamp": 0,
    "start_datetime_utc": "2025-09-14T08:00:00+00:00",
    "end_datetime_utc": "2025-09-14T10:30:00+00:00",
    "tournament": "Exort试验场 第四季",
    "team1": "CYBERSHOKE",
    "team2": "RUBY",
    "best_type": "BO3",
    "status": "已结束",
    "result": "2-0",
    "status_code": "2",
    "api_status": 2,
    "tournament_id": "csgo_tt_8692",
    "game_type": "CS:GO",
    "grade": "C级",
    "star": "0",
    "bo": "",
    "map_info": "",
    "round_name": "第二轮",
    "stage_desc": "小组赛 第二轮",
    "tournament_stage": "小组赛 第二轮",
    "team1_logo": "https://oss.5eplay.com/sport/csgo/team/12380.png",
    "team2_logo": "https://oss.5eplay.com/cloudx/p/sport/csgo/team/cnelpm4conkqks63eaj0.png",
    "tournament_logo": "https://oss.5eplay.com/cloudx/p/sport/csgo/tournament/d0trhpcconkt3legef50.png",
    "estimated_duration": 2.5
  },
  {
    "id": "csgo_mc_2385299",
    "start_timestamp": 1757836800,
    "end_timestamp": 0,
    "start_datetime_utc": "2025-09-14T08:00:00+00:00",
    "end_datetime_utc": "2025-09-14T10:30:00+00:00",
    "tournament": "FISSURE 裂变天地 2",
    "team1": "Mongolz",
    "team2": "LVG",
    "best_type": "BO3",
    "status": "已结束",
    "result": "2-0",
    "status_code": "2",
    "api_status": 2,
    "tournament_id": "csgo_tt_8064",
    "game_type": "CS:GO",
    "grade": "A级",
    "star": "2",
    "bo": "",
    "map_info": "",
    "round_name": "第二轮",
    "stage_desc": "小组赛 第二轮",
    "tournament_stage": "小组赛 第二轮",
    "team1_logo": "https://oss.5eplay.com/cloudx/p/sport/csgo/team/cotdagsconklgsjvhg10.png",
    "team2_logo": "https://oss.5eplay.com/sport/csgo/team/hz/cec3ssv4nfq43340vfu0.png",
    "tournament_logo": "https://oss.5eplay.com/cloudx/p/sport/csgo/tournament/d1qr6pcconkt3legerfg.png",
    "estimated_duration": 2.5
  },
  {
    "id": "csgo_mc_2385298",
    "start_timestamp": 1757836800,
    "end_timestamp": 0,
    "start_datetime_utc": "2025-09-14T08:00:00+00:00",
    "end_datetime_utc": "2025-09-14T10:30:00+00:00",
    "tournament": "FISSURE 裂变天地 2",
    "team1": " 3DMAX",
    "team2": "FaZe",
    "best_type": "BO3",
    "status": "已结束",
    "result": "1-2",
    "status_code": "2",
    "api_status": 2,
    "tournament_id": "csgo_tt_8064",
    "game_type": "CS:GO",
    "grade": "A级",
    "star": "2",
    "bo": "",
    "map_info": "",
    "round_name": "第二轮",
    "stage_desc": "小组赛 第二轮",
    "tournament_stage": "小组赛 第二轮",
    "team1_logo": "https://oss.5eplay.com/cloudx/p/sport/csgo/team/cssus2cconkotam81h1g.png",
    "team2_logo": "https://oss.5eplay.com/cloudx/p/sport/csgo/team/cm9qs5kconkqks63d75g.png",
    "tournament_logo": "https://oss.5eplay.com/cloudx/p/sport/csgo/tournament/d1qr6pcconkt3legerfg.png",
    "estimated_duration": 2.5
  },
  {
    "id": "csgo_mc_2385259",
    "start_timestamp": 1757836800,
    "end_timestamp": 0,
    "start_datetime_utc": "2025-09-14T08:00:00+00:00",
    "end_datetime_utc": "2025-09-14T10:30:00+00:00",
    "tournament": "欧洲职业联赛 系列赛2",
    "team1": "SINNERS",
    "team2": "Betera",
    "best_type": "BO3",
    "status": "已结束",
    "result": "2-0",
    "status_code": "2",
    "api_status": 2,
    "tournament_id": "csgo_tt_8660",
    "game_type": "CS:GO",
    "grade": "其他",
    "star": "0",
    "bo": "",
    "map_info": "",
    "round_name": "决赛",
    "stage_desc": "小组赛 败者组 决赛",
    "tournament_stage": "小组赛 败者组 决赛",
    "team1_logo": "https://oss.5eplay.com/sport/csgo/team/hz/cec3uq74nfq43340vq30.png",
    "team2_logo": "https://oss.5eplay.com/cloudx/p/sport/csgo/team/cnhs5n4conkqks63ec7g.png",
    "tournament_logo": "https://oss.5eplay.com/cloudx/p/sport/csgo/tournament/cqtimtcconkotam80b90.png",
    "estimated_duration": 2.5
  },
  {
    "id": "csgo_mc_2385605",
    "start_timestamp": 1757837400,
    "end_timestamp": 0,
    "start_datetime_utc": "2025-09-14T08:10:00+00:00",
    "end_datetime_utc": "2025-09-14T12:10:00+00:00",
    "tournament": "夜晚邀请赛 2025 亚太地区",
    "team1": "Mindfreak",
    "team2": "Animus Victoria",
    "best_type": "BO5",
    "status": "已结束",
    "result": "3-1",
    "status_code": "2",
    "api_status": 2,
    "tournament_id": "csgo_tt_8701",
    "game_type": "CS:GO",
    "grade": "其他",
    "star": "0",
    "bo": "",
    "map_info": "",
    "round_name": "决赛",
    "stage_desc": "淘汰赛 决赛",
    "tournament_stage": "淘汰赛 决赛",
    "team1_logo": "https://oss.5eplay.com/sport/csgo/team/hz/cec403n4nfq4334101m0.png",
    "team2_logo": "https://oss.5eplay.com/cloudx/p/sport/csgo/team/merge_d1o6n64conkt3legeqtg.png",
    "tournament_logo": "https://oss.5eplay.com/cloudx/p/sport/csgo/tournament/d2se83kconkqbk3bnmq0.png",
    "estimated_duration": 4.0
  },
  {
    "id": "csgo_mc_2385673",
    "start_timestamp": 1757840400,
    "end_timestamp": 0,
    "start_datetime_utc": "2025-09-14T09:00:00+00:00",
    "end_datetime_utc": "2025-09-14T11:30:00+00:00",
    "tournament": "罗马帝国之声杯 第二季",
    "team1": "FACEITPLAYERS",
    "team2": "TFD",
    "best_type": "BO3",
    "status": "已结束",
    "result": "2-0",
    "status_code": "2",
    "api_status": 2,
    "tournament_id": "csgo_tt_8699",
    "game_type": "CS:GO",
    "grade": "其他",
    "star": "0",
    "bo": "",
    "map_info": "",
    "round_name": "1/4决赛",
    "stage_desc": "淘汰赛 1/4决赛",
    "tournament_stage": "淘汰赛 1/4决赛",
    "team1_logo": "https://oss.5eplay.com/sport/csgo/team/null.png",
    "team2_logo": "https://oss.5eplay.com/sport/csgo/team/null.png",
    "tournament_logo": "https://oss.5eplay.com/cloudx/p/sport/csgo/tournament/d31ou3sconkqbk3bnnig.png",
    "estimated_duration": 2.5
  },
  {
    "id": "csgo_mc_2385674",
    "start_timestamp": 1757840400,
    "end_timestamp": 0,
    "start_datetime_utc": "2025-09-14T09:00:00+00:00",
    "end_datetime_utc": "2025-09-14T11:30:00+00:00",
    "tournament": "罗马帝国之声杯 第二季",
    "team1": "Gentle Mates",
    "team2": "Rebels",
    "best_type": "BO3",
    "status": "已结束",
    "result": "2-0",
    "status_code": "2",
    "api_status": 2,
    "tournament_id": "csgo_tt_8699",
    "game_type": "CS:GO",
    "grade": "其他",
    "star": "0",
    "bo": "",
    "map_info": "",
    "round_name": "1/4决赛",
    "stage_desc": "淘汰赛 1/4决赛",
    "tournament_stage": "淘汰赛 1/4决赛",
    "team1_logo": "https://oss.5eplay.com/cloudx/p/sport/csgo/team/d2seh4kconkqbk3bnmvg.png",
    "team2_logo": "https://oss.5eplay.com/cloudx/p/sport/csgo/team/cmmt574conkqks63div0.png",
    "tournament_logo": "https://oss.5eplay.com/cloudx/p/sport/csgo/tournament/d31ou3sconkqbk3bnnig.png",
    "estimated_duration": 2.5
  },
  {
    "id": "csgo_mc_2385761",
    "start_timestamp": 1757842800,
    "end_timestamp": 0,
    "start_datetime_utc": "2025-09-14T09:40:00+00:00",
    "end_datetime_utc": "2025-09-14T12:10:00+00:00",
    "tournament": "玉麒麟战斗巅峰第1赛季",
    "team1": "FengDa",
    "team2": "Just Swing",
    "best_type": "BO3",
    "status": "已结束",
    "result": "2-1",
    "status_code": "2",
    "api_status": 2,
    "tournament_id": "csgo_tt_8708",
    "game_type": "CS:GO",
    "grade": "其他",
    "star": "0",
    "bo": "",
    "map_info": "",
    "round_name": "决赛",
    "stage_desc": "淘汰赛 决赛",
    "tournament_stage": "淘汰赛 决赛",
    "team1_logo": "https://oss.5eplay.com/cloudx/p/sport/csgo/team/cu4f18cconkqmjpn7t0g.png",
    "team2_logo": "https://oss.5eplay.com/cloudx/p/sport/csgo/team/cu4eflkconkqmjpn7t00.png",
    "tournament_logo": "https://oss.5eplay.com/cloudx/p/sport/csgo/tournament/d338e0sconkqbk3bno90.png",
    "estimated_duration": 2.5
  },
  {
    "id": "csgo_mc_2385469",
    "start_timestamp": 1757844000,
    "end_timestamp": 0,
    "start_datetime_utc": "2025-09-14T10:00:00+00:00",
    "end_datetime_utc": "2025-09-14T12:30:00+00:00",
    "tournament": "Betclic Clash 夏季 2025",
    "team1": "FNC",
    "team2": "Nemiga",
    "best_type": "BO3",
    "status": "已结束",
    "result": "2-0",
    "status_code": "2",
    "api_status": 2,
    "tournament_id": "csgo_tt_8670",
    "game_type": "CS:GO",
    "grade": "其他",
    "star": "0",
    "bo": "",
    "map_info": "",
    "round_name": "半决赛",
    "stage_desc": "淘汰赛 半决赛",
    "tournament_stage": "淘汰赛 半决赛",
    "team1_logo": "https://oss.5eplay.com/sport/csgo/team/hz/cec3pkn4nfq43340upig.png",
    "team2_logo": "https://oss.5eplay.com/cloudx/p/sport/csgo/team/ch9otcv4nfqe2nie4tc0.png",
    "tournament_logo": "https://oss.5eplay.com/cloudx/p/sport/csgo/tournament/d2o65gsconkqbk3bnl60.png",
    "estimated_duration": 2.5
  },
  {
    "id": "csgo_mc_2385762",
    "start_timestamp": 1757845800,
    "end_timestamp": 0,
    "start_datetime_utc": "2025-09-14T10:30:00+00:00",
    "end_datetime_utc": "2025-09-14T13:00:00+00:00",
    "tournament": "CS 亚洲邀请赛 2025 中国 公开预选赛",
    "team1": "TakeMeAway",
    "team2": "RA",
    "best_type": "BO3",
    "status": "已结束",
    "result": "2-0",
    "status_code": "2",
    "api_status": 2,
    "tournament_id": "csgo_tt_8704",
    "game_type": "CS:GO",
    "grade": "",
    "star": "0",
    "bo": "",
    "map_info": "",
    "round_name": "决赛",
    "stage_desc": "淘汰赛 决赛",
    "tournament_stage": "淘汰赛 决赛",
    "team1_logo": "https://oss.5eplay.com/sport/csgo/team/null.png",
    "team2_logo": "https://oss.5eplay.com/cloudx/p/sport/csgo/team/cgm4f374nfqe2nie3tig.png",
    "tournament_logo": "https://oss.5eplay.com/cloudx/p/sport/csgo/tournament/ctlqo7kconkqmjpn7hmg.png",
    "estimated_duration": 2.5
  },
  {
    "id": "csgo_mc_2385260",
    "start_timestamp": 1757845800,
    "end_timestamp": 0,
    "start_datetime_utc": "2025-09-14T10:30:00+00:00",
    "end_datetime_utc": "2025-09-14T13:00:00+00:00",
    "tournament": "欧洲职业联赛 系列赛2",
    "team1": "EYE",
    "team2": "ARCRED",
    "best_type": "BO3",
    "status": "已结束",
    "result": "0-2",
    "status_code": "2",
    "api_status": 2,
    "tournament_id": "csgo_tt_8660",
    "game_type": "CS:GO",
    "grade": "其他",
    "star": "0",
    "bo": "",
    "map_info": "",
    "round_name": "决赛",
    "stage_desc": "小组赛 败者组 决赛",
    "tournament_stage": "小组赛 败者组 决赛",
    "team1_logo": "https://oss.5eplay.com/sport/csgo/team/merge_ceihebn4nfq4334151j0.png",
    "team2_logo": "https://oss.5eplay.com/cloudx/p/sport/csgo/team/cmvq29sconkqks63dsl0.png",
    "tournament_logo": "https://oss.5eplay.com/cloudx/p/sport/csgo/tournament/cqtimtcconkotam80b90.png",
    "estimated_duration": 2.5
  },
  {
    "id": "csgo_mc_2385301",
    "start_timestamp": 1757846700,
    "end_timestamp": 0,
    "start_datetime_utc": "2025-09-14T10:45:00+00:00",
    "end_datetime_utc": "2025-09-14T13:15:00+00:00",
    "tournament": "FISSURE 裂变天地 2",
    "team1": "VP",
    "team2": "Astralis",
    "best_type": "BO3",
    "status": "已结束",
    "result": "0-2",
    "status_code": "2",
    "api_status": 2,
    "tournament_id": "csgo_tt_8064",
    "game_type": "CS:GO",
    "grade": "A级",
    "star": "2",
    "bo": "",
    "map_info": "",
    "round_name": "第二轮",
    "stage_desc": "小组赛 第二轮",
    "tournament_stage": "小组赛 第二轮",
    "team1_logo": "https://oss.5eplay.com/cloudx/p/sport/csgo/team/ct1uoncconkotam81hkg.png",
    "team2_logo": "https://oss.5eplay.com/cloudx/p/sport/csgo/team/ch9oh3n4nfqe2nie4t10.png",
    "tournament_logo": "https://oss.5eplay.com/cloudx/p/sport/csgo/tournament/d1qr6pcconkt3legerfg.png",
    "estimated_duration": 2.5
  },
  {
    "id": "csgo_mc_2385528",
    "start_timestamp": 1757847600,
    "end_timestamp": 0,
    "start_datetime_utc": "2025-09-14T11:00:00+00:00",
    "end_datetime_utc": "2025-09-14T13:30:00+00:00",
    "tournament": "CCT 第3赛季 欧洲系列赛 6",
    "team1": "GUN5",
    "team2": "RUBY",
    "best_type": "BO3",
    "status": "已结束",
    "result": "2-0",
    "status_code": "2",
    "api_status": 2,
    "tournament_id": "csgo_tt_8680",
    "game_type": "CS:GO",
    "grade": "C级",
    "star": "0",
    "bo": "",
    "map_info": "",
    "round_name": "第三轮",
    "stage_desc": "小组赛 第三轮",
    "tournament_stage": "小组赛 第三轮",
    "team1_logo": "https://oss.5eplay.com/sport/csgo/team/12471.png",
    "team2_logo": "https://oss.5eplay.com/cloudx/p/sport/csgo/team/cnelpm4conkqks63eaj0.png",
    "tournament_logo": "https://oss.5eplay.com/cloudx/p/sport/csgo/tournament/d0guuusconkt3legeagg.png",
    "estimated_duration": 2.5
  },
  {
    "id": "csgo_mc_2385458",
    "start_timestamp": 1757847600,
    "end_timestamp": 0,
    "start_datetime_utc": "2025-09-14T11:00:00+00:00",
    "end_datetime_utc": "2025-09-14T13:30:00+00:00",
    "tournament": "Exort试验场 第四季",
    "team1": "Betclic",
    "team2": "Spirit.A",
    "best_type": "BO3",
    "status": "已结束",
    "result": "1-2",
    "status_code": "2",
    "api_status": 2,
    "tournament_id": "csgo_tt_8692",
    "game_type": "CS:GO",
    "grade": "C级",
    "star": "0",
    "bo": "",
    "map_info": "",
    "round_name": "第二轮",
    "stage_desc": "小组赛 第二轮",
    "tournament_stage": "小组赛 第二轮",
    "team1_logo": "https://oss.5eplay.com/cloudx/p/sport/csgo/team/d0enhisconkt3lege8v0.png",
    "team2_logo": "https://oss.5eplay.com/sport/csgo/team/merge_ceihkav4nfq4334151rg.png",
    "tournament_logo": "https://oss.5eplay.com/cloudx/p/sport/csgo/tournament/d0trhpcconkt3legef50.png",
    "estimated_duration": 2.5
  },
  {
    "id": "csgo_mc_2385300",
    "start_timestamp": 1757848500,
    "end_timestamp": 0,
    "start_datetime_utc": "2025-09-14T11:15:00+00:00",
    "end_datetime_utc": "2025-09-14T13:45:00+00:00",
    "tournament": "FISSURE 裂变天地 2",
    "team1": "Falcons",
    "team2": "Legacy",
    "best_type": "BO3",
    "status": "已结束",
    "result": "2-0",
    "status_code": "2",
    "api_status": 2,
    "tournament_id": "csgo_tt_8064",
    "game_type": "CS:GO",
    "grade": "A级",
    "star": "1",
    "bo": "",
    "map_info": "",
    "round_name": "第二轮",
    "stage_desc": "小组赛 第二轮",
    "tournament_stage": "小组赛 第二轮",
    "team1_logo": "https://oss.5eplay.com/cloudx/p/sport/csgo/team/cm0k2q4conkqks63d37g.png",
    "team2_logo": "https://oss.5eplay.com/cloudx/p/sport/csgo/team/ck9evp4conkqks63bksg.png",
    "tournament_logo": "https://oss.5eplay.com/cloudx/p/sport/csgo/tournament/d1qr6pcconkt3legerfg.png",
    "estimated_duration": 2.5
  },
  {
    "id": "csgo_mc_2385676",
    "start_timestamp": 1757849400,
    "end_timestamp": 0,
    "start_datetime_utc": "2025-09-14T11:30:00+00:00",
    "end_datetime_utc": "2025-09-14T14:00:00+00:00",
    "tournament": "罗马帝国之声杯 第二季",
    "team1": "Rhyno YNG",
    "team2": "AGRICOLA",
    "best_type": "BO3",
    "status": "已结束",
    "result": "2-0",
    "status_code": "2",
    "api_status": 2,
    "tournament_id": "csgo_tt_8699",
    "game_type": "CS:GO",
    "grade": "其他",
    "star": "0",
    "bo": "",
    "map_info": "",
    "round_name": "1/4决赛",
    "stage_desc": "淘汰赛 1/4决赛",
    "tournament_stage": "淘汰赛 1/4决赛",
    "team1_logo": "https://oss.5eplay.com/sport/csgo/team/null.png",
    "team2_logo": "https://oss.5eplay.com/sport/csgo/team/null.png",
    "tournament_logo": "https://oss.5eplay.com/cloudx/p/sport/csgo/tournament/d31ou3sconkqbk3bnnig.png",
    "estimated_duration": 2.5
  },
  {
    "id": "csgo_mc_2385557",
    "start_timestamp": 1757849400,
    "end_timestamp": 0,
    "start_datetime_utc": "2025-09-14T11:30:00+00:00",
    "end_datetime_utc": "2025-09-14T14:00:00+00:00",
    "tournament": "CCT 第3赛季 欧洲系列赛 7 封闭预选赛",
    "team1": "NIP Impact",
    "team2": "ex-HEROIC Academy",
    "best_type": "BO3",
    "status": "已结束",
    "result": "0-2",
    "status_code": "2",
    "api_status": 2,
    "tournament_id": "csgo_tt_8695",
    "game_type": "CS:GO",
    "grade": "",
    "star": "0",
    "bo": "",
    "map_info": "",
    "round_name": "首轮",
    "stage_desc": "小组赛 败者组 首轮",
    "tournament_stage": "小组赛 败者组 首轮",
    "team1_logo": "https://oss.5eplay.com/sport/csgo/team/cetob4pll806civqft8g.png",
    "team2_logo": "https://oss.5eplay.com/sport/csgo/team/null.png",
    "tournament_logo": "https://oss.5eplay.com/cloudx/p/sport/csgo/tournament/d0guuusconkt3legeagg.png",
    "estimated_duration": 2.5
  },
  {
    "id": "csgo_mc_2385675",
    "start_timestamp": 1757851200,
    "end_timestamp": 0,
    "start_datetime_utc": "2025-09-14T12:00:00+00:00",
    "end_datetime_utc": "2025-09-14T14:30:00+00:00",
    "tournament": "罗马帝国之声杯 第二季",
    "team1": "SAW",
    "team2": "Famalicão",
    "best_type": "BO3",
    "status": "已结束",
    "result": "2-0",
    "status_code": "2",
    "api_status": 2,
    "tournament_id": "csgo_tt_8699",
    "game_type": "CS:GO",
    "grade": "其他",
    "star": "0",
    "bo": "",
    "map_info": "",
    "round_name": "1/4决赛",
    "stage_desc": "淘汰赛 1/4决赛",
    "tournament_stage": "淘汰赛 1/4决赛",
    "team1_logo": "https://oss.5eplay.com/cloudx/p/sport/csgo/team/merge_cldgrokconkqks63cjk0.png",
    "team2_logo": "https://oss.5eplay.com/cloudx/p/sport/csgo/team/d2gjvpkconkt3legf0t0.png",
    "tournament_logo": "https://oss.5eplay.com/cloudx/p/sport/csgo/tournament/d31ou3sconkqbk3bnnig.png",
    "estimated_duration": 2.5
  },
  {
    "id": "csgo_mc_2385680",
    "start_timestamp": 1757854800,
    "end_timestamp": 0,
    "start_datetime_utc": "2025-09-14T13:00:00+00:00",
    "end_datetime_utc": "2025-09-14T15:30:00+00:00",
    "tournament": "CS 亚洲邀请赛 2025 亚洲其他地区 公开预选赛",
    "team1": "AE",
    "team2": "Beyman",
    "best_type": "BO3",
    "status": "已结束",
    "result": "2-0",
    "status_code": "2",
    "api_status": 2,
    "tournament_id": "csgo_tt_8706",
    "game_type": "CS:GO",
    "grade": "",
    "star": "0",
    "bo": "",
    "map_info": "",
    "round_name": "决赛",
    "stage_desc": "淘汰赛 决赛",
    "tournament_stage": "淘汰赛 决赛",
    "team1_logo": "https://oss.5eplay.com/sport/csgo/team/hz/cec3u5n4nfq43340vmsg.png",
    "team2_logo": "https://oss.5eplay.com/sport/csgo/team/null.png",
    "tournament_logo": "https://oss.5eplay.com/cloudx/p/sport/csgo/tournament/ctlqo7kconkqmjpn7hmg.png",
    "estimated_duration": 2.5
  },
  {
    "id": "csgo_mc_2385592",
    "start_timestamp": 1757854800,
    "end_timestamp": 0,
    "start_datetime_utc": "2025-09-14T13:00:00+00:00",
    "end_datetime_utc": "2025-09-14T15:30:00+00:00",
    "tournament": " CCT 第3赛季 南美系列赛4",
    "team1": "9z",
    "team2": "ShindeN",
    "best_type": "BO3",
    "status": "已结束",
    "result": "1-2",
    "status_code": "2",
    "api_status": 2,
    "tournament_id": "csgo_tt_8681",
    "game_type": "CS:GO",
    "grade": "其他",
    "star": "0",
    "bo": "",
    "map_info": "",
    "round_name": "十六强",
    "stage_desc": "淘汰赛 十六强",
    "tournament_stage": "淘汰赛 十六强",
    "team1_logo": "https://oss.5eplay.com/cloudx/p/sport/csgo/team/co12ihcconklgsjvgua0.png",
    "team2_logo": "https://oss.5eplay.com/sport/csgo/team/12959.png",
    "tournament_logo": "https://oss.5eplay.com/cloudx/p/sport/csgo/tournament/d1vrbfcconkt3leget7g.png",
    "estimated_duration": 2.5
  },
  {
    "id": "csgo_mc_2384977",
    "start_timestamp": 1757854800,
    "end_timestamp": 0,
    "start_datetime_utc": "2025-09-14T13:00:00+00:00",
    "end_datetime_utc": "2025-09-14T15:30:00+00:00",
    "tournament": "Tipsport 夏季杯 2025 决赛",
    "team1": "SINNERS",
    "team2": "UNiTY",
    "best_type": "BO3",
    "status": "已结束",
    "result": "2-0",
    "status_code": "2",
    "api_status": 2,
    "tournament_id": "csgo_tt_8657",
    "game_type": "CS:GO",
    "grade": "其他",
    "star": "0",
    "bo": "",
    "map_info": "",
    "round_name": "决赛",
    "stage_desc": "淘汰赛 败者组 决赛",
    "tournament_stage": "淘汰赛 败者组 决赛",
    "team1_logo": "https://oss.5eplay.com/sport/csgo/team/hz/cec3uq74nfq43340vq30.png",
    "team2_logo": "https://oss.5eplay.com/cloudx/p/sport/csgo/team/cjrh38cconkqks63b5a0.png",
    "tournament_logo": "https://oss.5eplay.com/cloudx/p/sport/csgo/tournament/cuuqf44conkqmjpn8dl0.png",
    "estimated_duration": 2.5
  },
  {
    "id": "csgo_mc_2385303",
    "start_timestamp": 1757856300,
    "end_timestamp": 0,
    "start_datetime_utc": "2025-09-14T13:25:00+00:00",
    "end_datetime_utc": "2025-09-14T15:55:00+00:00",
    "tournament": "FISSURE 裂变天地 2",
    "team1": "GL",
    "team2": "Liquid",
    "best_type": "BO3",
    "status": "已结束",
    "result": "2-0",
    "status_code": "2",
    "api_status": 2,
    "tournament_id": "csgo_tt_8064",
    "game_type": "CS:GO",
    "grade": "A级",
    "star": "2",
    "bo": "",
    "map_info": "",
    "round_name": "第二轮",
    "stage_desc": "小组赛 第二轮",
    "tournament_stage": "小组赛 第二轮",
    "team1_logo": "https://oss.5eplay.com/cloudx/p/sport/csgo/team/cldgn5kconkqks63cjg0.png",
    "team2_logo": "https://oss.5eplay.com/cloudx/p/sport/csgo/team/merge_cm0fk94conkqks63d2fg.png",
    "tournament_logo": "https://oss.5eplay.com/cloudx/p/sport/csgo/tournament/d1qr6pcconkt3legerfg.png",
    "estimated_duration": 2.5
  },
  {
    "id": "csgo_mc_2385470",
    "start_timestamp": 1757857200,
    "end_timestamp": 0,
    "start_datetime_utc": "2025-09-14T13:40:00+00:00",
    "end_datetime_utc": "2025-09-14T16:10:00+00:00",
    "tournament": "Betclic Clash 夏季 2025",
    "team1": "ECSTATIC",
    "team2": "BIG",
    "best_type": "BO3",
    "status": "已结束",
    "result": "2-1",
    "status_code": "2",
    "api_status": 2,
    "tournament_id": "csgo_tt_8670",
    "game_type": "CS:GO",
    "grade": "其他",
    "star": "0",
    "bo": "",
    "map_info": "",
    "round_name": "半决赛",
    "stage_desc": "淘汰赛 半决赛",
    "tournament_stage": "淘汰赛 半决赛",
    "team1_logo": "https://oss.5eplay.com/cloudx/p/sport/csgo/team/ch5k0tf4nfqe2nie4ohg.png",
    "team2_logo": "https://oss.5eplay.com/sport/csgo/team/merge_cgdr7u9ll806h1bg2os0.png",
    "tournament_logo": "https://oss.5eplay.com/cloudx/p/sport/csgo/tournament/d2o65gsconkqbk3bnl60.png",
    "estimated_duration": 2.5
  },
  {
    "id": "csgo_mc_2385529",
    "start_timestamp": 1757858400,
    "end_timestamp": 0,
    "start_datetime_utc": "2025-09-14T14:00:00+00:00",
    "end_datetime_utc": "2025-09-14T16:30:00+00:00",
    "tournament": "CCT 第3赛季 欧洲系列赛 6",
    "team1": "HOTU",
    "team2": "Reason",
    "best_type": "BO3",
    "status": "已结束",
    "result": "2-0",
    "status_code": "2",
    "api_status": 2,
    "tournament_id": "csgo_tt_8680",
    "game_type": "CS:GO",
    "grade": "C级",
    "star": "0",
    "bo": "",
    "map_info": "",
    "round_name": "第三轮",
    "stage_desc": "小组赛 第三轮",
    "tournament_stage": "小组赛 第三轮",
    "team1_logo": "https://oss.5eplay.com/sport/csgo/team/merge_ceimb1v4nfq4334153a0.png",
    "team2_logo": "https://oss.5eplay.com/sport/csgo/team/hz/cec3pj74nfq43340up1g.png",
    "tournament_logo": "https://oss.5eplay.com/cloudx/p/sport/csgo/tournament/d0guuusconkt3legeagg.png",
    "estimated_duration": 2.5
  },
  {
    "id": "csgo_mc_2385459",
    "start_timestamp": 1757858400,
    "end_timestamp": 0,
    "start_datetime_utc": "2025-09-14T14:00:00+00:00",
    "end_datetime_utc": "2025-09-14T16:30:00+00:00",
    "tournament": "Exort试验场 第四季",
    "team1": "Betera",
    "team2": "JJH",
    "best_type": "BO3",
    "status": "已结束",
    "result": "2-0",
    "status_code": "2",
    "api_status": 2,
    "tournament_id": "csgo_tt_8692",
    "game_type": "CS:GO",
    "grade": "C级",
    "star": "0",
    "bo": "",
    "map_info": "",
    "round_name": "第二轮",
    "stage_desc": "小组赛 第二轮",
    "tournament_stage": "小组赛 第二轮",
    "team1_logo": "https://oss.5eplay.com/cloudx/p/sport/csgo/team/cnhs5n4conkqks63ec7g.png",
    "team2_logo": "https://oss.5eplay.com/cloudx/p/sport/csgo/team/d00eh74conkt3lege5ag.png",
    "tournament_logo": "https://oss.5eplay.com/cloudx/p/sport/csgo/tournament/d0trhpcconkt3legef50.png",
    "estimated_duration": 2.5
  },
  {
    "id": "csgo_mc_2385414",
    "start_timestamp": 1757858400,
    "end_timestamp": 0,
    "start_datetime_utc": "2025-09-14T14:00:00+00:00",
    "end_datetime_utc": "2025-09-14T16:30:00+00:00",
    "tournament": "银河之战 2025 第4阶段 公开预选",
    "team1": "CPH Wolves",
    "team2": "MINLATE",
    "best_type": "BO3",
    "status": "已结束",
    "result": "2-0",
    "status_code": "2",
    "api_status": 2,
    "tournament_id": "csgo_tt_8691",
    "game_type": "CS:GO",
    "grade": "其他",
    "star": "0",
    "bo": "",
    "map_info": "",
    "round_name": "首轮",
    "stage_desc": "小组赛 胜者组 首轮",
    "tournament_stage": "小组赛 胜者组 首轮",
    "team1_logo": "https://oss.5eplay.com/sport/csgo/team/hz/cec3pfv4nfq43340unug.png",
    "team2_logo": "https://oss.5eplay.com/sport/csgo/team/null.png",
    "tournament_logo": "https://oss.5eplay.com/cloudx/p/sport/csgo/tournament/d140b3kconkt3legekmg.png",
    "estimated_duration": 2.5
  },
  {
    "id": "csgo_mc_2385302",
    "start_timestamp": 1757859300,
    "end_timestamp": 0,
    "start_datetime_utc": "2025-09-14T14:15:00+00:00",
    "end_datetime_utc": "2025-09-14T16:45:00+00:00",
    "tournament": "FISSURE 裂变天地 2",
    "team1": "Aurora",
    "team2": "TYLOO",
    "best_type": "BO3",
    "status": "已结束",
    "result": "2-0",
    "status_code": "2",
    "api_status": 2,
    "tournament_id": "csgo_tt_8064",
    "game_type": "CS:GO",
    "grade": "A级",
    "star": "2",
    "bo": "",
    "map_info": "",
    "round_name": "第二轮",
    "stage_desc": "小组赛 第二轮",
    "tournament_stage": "小组赛 第二轮",
    "team1_logo": "https://oss.5eplay.com/cloudx/p/sport/csgo/team/cgrnhlf4nfqe2nie40o0.png",
    "team2_logo": "https://oss.5eplay.com/sport/csgo/team/hz/cec3pjf4nfq43340up40.png",
    "tournament_logo": "https://oss.5eplay.com/cloudx/p/sport/csgo/tournament/d1qr6pcconkt3legerfg.png",
    "estimated_duration": 2.5
  },
  {
    "id": "csgo_mc_2385678",
    "start_timestamp": 1757860200,
    "end_timestamp": 0,
    "start_datetime_utc": "2025-09-14T14:30:00+00:00",
    "end_datetime_utc": "2025-09-14T17:00:00+00:00",
    "tournament": "罗马帝国之声杯 第二季",
    "team1": "Gentle Mates",
    "team2": "Rhyno YNG",
    "best_type": "BO3",
    "status": "已结束",
    "result": "2-0",
    "status_code": "2",
    "api_status": 2,
    "tournament_id": "csgo_tt_8699",
    "game_type": "CS:GO",
    "grade": "其他",
    "star": "0",
    "bo": "",
    "map_info": "",
    "round_name": "半决赛",
    "stage_desc": "淘汰赛 半决赛",
    "tournament_stage": "淘汰赛 半决赛",
    "team1_logo": "https://oss.5eplay.com/cloudx/p/sport/csgo/team/d2seh4kconkqbk3bnmvg.png",
    "team2_logo": "https://oss.5eplay.com/sport/csgo/team/null.png",
    "tournament_logo": "https://oss.5eplay.com/cloudx/p/sport/csgo/tournament/d31ou3sconkqbk3bnnig.png",
    "estimated_duration": 2.5
  },
  {
    "id": "csgo_mc_2385559",
    "start_timestamp": 1757860200,
    "end_timestamp": 0,
    "start_datetime_utc": "2025-09-14T14:30:00+00:00",
    "end_datetime_utc": "2025-09-14T17:00:00+00:00",
    "tournament": "CCT 第3赛季 欧洲系列赛 7 封闭预选赛",
    "team1": "ex-8Sins",
    "team2": "Mousquetaires",
    "best_type": "BO3",
    "status": "已结束",
    "result": "1-2",
    "status_code": "2",
    "api_status": 2,
    "tournament_id": "csgo_tt_8695",
    "game_type": "CS:GO",
    "grade": "",
    "star": "0",
    "bo": "",
    "map_info": "",
    "round_name": "决赛",
    "stage_desc": "小组赛 胜者组 决赛",
    "tournament_stage": "小组赛 胜者组 决赛",
    "team1_logo": "https://oss.5eplay.com/sport/csgo/team/null.png",
    "team2_logo": "https://oss.5eplay.com/cloudx/p/sport/csgo/team/merge_d0lclrsconkt3legecb0.png",
    "tournament_logo": "https://oss.5eplay.com/cloudx/p/sport/csgo/tournament/d0guuusconkt3legeagg.png",
    "estimated_duration": 2.5
  },
  {
    "id": "csgo_mc_2385677",
    "start_timestamp": 1757861100,
    "end_timestamp": 0,
    "start_datetime_utc": "2025-09-14T14:45:00+00:00",
    "end_datetime_utc": "2025-09-14T17:15:00+00:00",
    "tournament": "罗马帝国之声杯 第二季",
    "team1": "FACEITPLAYERS",
    "team2": "SAW",
    "best_type": "BO3",
    "status": "已结束",
    "result": "0-2",
    "status_code": "2",
    "api_status": 2,
    "tournament_id": "csgo_tt_8699",
    "game_type": "CS:GO",
    "grade": "其他",
    "star": "0",
    "bo": "",
    "map_info": "",
    "round_name": "半决赛",
    "stage_desc": "淘汰赛 半决赛",
    "tournament_stage": "淘汰赛 半决赛",
    "team1_logo": "https://oss.5eplay.com/sport/csgo/team/null.png",
    "team2_logo": "https://oss.5eplay.com/cloudx/p/sport/csgo/team/merge_cldgrokconkqks63cjk0.png",
    "tournament_logo": "https://oss.5eplay.com/cloudx/p/sport/csgo/tournament/d31ou3sconkqbk3bnnig.png",
    "estimated_duration": 2.5
  },
  {
    "id": "csgo_mc_2385612",
    "start_timestamp": 1757862000,
    "end_timestamp": 0,
    "start_datetime_utc": "2025-09-14T15:00:00+00:00",
    "end_datetime_utc": "2025-09-14T17:30:00+00:00",
    "tournament": "ESEA发展联赛 第54赛季 欧洲",
    "team1": "Insilio",
    "team2": "Nuclear TigeRES",
    "best_type": "BO3",
    "status": "已结束",
    "result": "2-0",
    "status_code": "2",
    "api_status": 2,
    "tournament_id": "csgo_tt_8676",
    "game_type": "CS:GO",
    "grade": "其他",
    "star": "0",
    "bo": "",
    "map_info": "",
    "round_name": "第5轮",
    "stage_desc": "淘汰赛 败者组 第5轮",
    "tournament_stage": "淘汰赛 败者组 第5轮",
    "team1_logo": "https://oss.5eplay.com/cloudx/p/sport/csgo/team/merge_ch9qu9f4nfqe2nie4tvg.png",
    "team2_logo": "https://oss.5eplay.com/cloudx/p/sport/csgo/team/cup4jdkconkqmjpn8avg.png",
    "tournament_logo": "https://oss.5eplay.com/sport/csgo/event/8065.png",
    "estimated_duration": 2.5
  },
  {
    "id": "csgo_mc_2384978",
    "start_timestamp": 1757863200,
    "end_timestamp": 0,
    "start_datetime_utc": "2025-09-14T15:20:00+00:00",
    "end_datetime_utc": "2025-09-14T17:50:00+00:00",
    "tournament": "Tipsport 夏季杯 2025 决赛",
    "team1": "ECLOT",
    "team2": "SINNERS",
    "best_type": "BO3",
    "status": "进行中",
    "result": "1-1",
    "status_code": "1",
    "api_status": 1,
    "tournament_id": "csgo_tt_8657",
    "game_type": "CS:GO",
    "grade": "其他",
    "star": "0",
    "bo": "",
    "map_info": "",
    "round_name": "",
    "stage_desc": "淘汰赛  ",
    "tournament_stage": "淘汰赛",
    "team1_logo": "https://oss.5eplay.com/sport/csgo/team/hz/cec3r574nfq43340v6e0.png",
    "team2_logo": "https://oss.5eplay.com/sport/csgo/team/hz/cec3uq74nfq43340vq30.png",
    "tournament_logo": "https://oss.5eplay.com/cloudx/p/sport/csgo/tournament/cuuqf44conkqmjpn8dl0.png",
    "estimated_duration": 2.5
  },
  {
    "id": "csgo_mc_2385305",
    "start_timestamp": 1757865000,
    "end_timestamp": 0,
    "start_datetime_utc": "2025-09-14T15:50:00+00:00",
    "end_datetime_utc": "2025-09-14T18:20:00+00:00",
    "tournament": "FISSURE 裂变天地 2",
    "team1": "Heroic",
    "team2": "paiN",
    "best_type": "BO3",
    "status": "进行中",
    "result": "1-1",
    "status_code": "1",
    "api_status": 1,
    "tournament_id": "csgo_tt_8064",
    "game_type": "CS:GO",
    "grade": "A级",
    "star": "2",
    "bo": "",
    "map_info": "",
    "round_name": "第二轮",
    "stage_desc": "小组赛 第二轮",
    "tournament_stage": "小组赛 第二轮",
    "team1_logo": "https://oss.5eplay.com/sport/csgo/team/cgeh6n9ll806h1bg2osg.png",
    "team2_logo": "https://oss.5eplay.com/cloudx/p/sport/csgo/team/merge_chae3jf4nfqe2nie4un0.png",
    "tournament_logo": "https://oss.5eplay.com/cloudx/p/sport/csgo/tournament/d1qr6pcconkt3legerfg.png",
    "estimated_duration": 2.5
  },
  {
    "id": "csgo_mc_2385593",
    "start_timestamp": 1757865600,
    "end_timestamp": 0,
    "start_datetime_utc": "2025-09-14T16:00:00+00:00",
    "end_datetime_utc": "2025-09-14T18:30:00+00:00",
    "tournament": " CCT 第3赛季 南美系列赛4",
    "team1": "ODDIK",
    "team2": "KRÜ",
    "best_type": "BO3",
    "status": "进行中",
    "result": "1-1",
    "status_code": "1",
    "api_status": 1,
    "tournament_id": "csgo_tt_8681",
    "game_type": "CS:GO",
    "grade": "其他",
    "star": "0",
    "bo": "",
    "map_info": "",
    "round_name": "十六强",
    "stage_desc": "淘汰赛 十六强",
    "tournament_stage": "淘汰赛 十六强",
    "team1_logo": "https://oss.5eplay.com/cloudx/p/sport/csgo/team/cla6qasconkqks63cgjg.png",
    "team2_logo": "https://oss.5eplay.com/sport/csgo/team/10900.png",
    "tournament_logo": "https://oss.5eplay.com/cloudx/p/sport/csgo/tournament/d1vrbfcconkt3leget7g.png",
    "estimated_duration": 2.5
  },
  {
    "id": "csgo_mc_2385415",
    "start_timestamp": 1757869200,
    "end_timestamp": 0,
    "start_datetime_utc": "2025-09-14T17:00:00+00:00",
    "end_datetime_utc": "2025-09-14T19:30:00+00:00",
    "tournament": "银河之战 2025 第4阶段 公开预选",
    "team1": "EYE",
    "team2": "Khan",
    "best_type": "BO3",
    "status": "进行中",
    "result": "1-0",
    "status_code": "1",
    "api_status": 1,
    "tournament_id": "csgo_tt_8691",
    "game_type": "CS:GO",
    "grade": "其他",
    "star": "0",
    "bo": "",
    "map_info": "",
    "round_name": "首轮",
    "stage_desc": "小组赛 胜者组 首轮",
    "tournament_stage": "小组赛 胜者组 首轮",
    "team1_logo": "https://oss.5eplay.com/sport/csgo/team/merge_ceihebn4nfq4334151j0.png",
    "team2_logo": "https://oss.5eplay.com/cloudx/p/sport/csgo/team/merge_d2gk2gkconkt3legf0v0.png",
    "tournament_logo": "https://oss.5eplay.com/cloudx/p/sport/csgo/tournament/d140b3kconkt3legekmg.png",
    "estimated_duration": 2.5
  },
  {
    "id": "csgo_mc_2385460",
    "start_timestamp": 1757869200,
    "end_timestamp": 0,
    "start_datetime_utc": "2025-09-14T17:00:00+00:00",
    "end_datetime_utc": "2025-09-14T19:30:00+00:00",
    "tournament": "Exort试验场 第四季",
    "team1": "Sangal",
    "team2": "GUN5",
    "best_type": "BO3",
    "status": "进行中",
    "result": "1-0",
    "status_code": "1",
    "api_status": 1,
    "tournament_id": "csgo_tt_8692",
    "game_type": "CS:GO",
    "grade": "C级",
    "star": "0",
    "bo": "",
    "map_info": "",
    "round_name": "第二轮",
    "stage_desc": "小组赛 第二轮",
    "tournament_stage": "小组赛 第二轮",
    "team1_logo": "https://oss.5eplay.com/sport/csgo/team/hz/cec3ui74nfq43340vosg.png",
    "team2_logo": "https://oss.5eplay.com/sport/csgo/team/12471.png",
    "tournament_logo": "https://oss.5eplay.com/cloudx/p/sport/csgo/tournament/d0trhpcconkt3legef50.png",
    "estimated_duration": 2.5
  },
  {
    "id": "csgo_mc_2385530",
    "start_timestamp": 1757869200,
    "end_timestamp": 0,
    "start_datetime_utc": "2025-09-14T17:00:00+00:00",
    "end_datetime_utc": "2025-09-14T19:30:00+00:00",
    "tournament": "CCT 第3赛季 欧洲系列赛 6",
    "team1": "ESC",
    "team2": "CYBERSHOKE",
    "best_type": "BO3",
    "status": "进行中",
    "result": "0-1",
    "status_code": "1",
    "api_status": 1,
    "tournament_id": "csgo_tt_8680",
    "game_type": "CS:GO",
    "grade": "C级",
    "star": "0",
    "bo": "",
    "map_info": "",
    "round_name": "第三轮",
    "stage_desc": "小组赛 第三轮",
    "tournament_stage": "小组赛 第三轮",
    "team1_logo": "https://oss.5eplay.com/cloudx/p/sport/csgo/team/cnl75mkconklgsjvgk1g.png",
    "team2_logo": "https://oss.5eplay.com/sport/csgo/team/12380.png",
    "tournament_logo": "https://oss.5eplay.com/cloudx/p/sport/csgo/tournament/d0guuusconkt3legeagg.png",
    "estimated_duration": 2.5
  },
  {
    "id": "csgo_mc_2385304",
    "start_timestamp": 1757870100,
    "end_timestamp": 0,
    "start_datetime_utc": "2025-09-14T17:15:00+00:00",
    "end_datetime_utc": "2025-09-14T19:45:00+00:00",
    "tournament": "FISSURE 裂变天地 2",
    "team1": "FURIA",
    "team2": "G2",
    "best_type": "BO3",
    "status": "进行中",
    "result": "1-0",
    "status_code": "1",
    "api_status": 1,
    "tournament_id": "csgo_tt_8064",
    "game_type": "CS:GO",
    "grade": "A级",
    "star": "3",
    "bo": "",
    "map_info": "",
    "round_name": "第二轮",
    "stage_desc": "小组赛 第二轮",
    "tournament_stage": "小组赛 第二轮",
    "team1_logo": "https://oss.5eplay.com/sport/csgo/team/cgcl4u1ll806h1bg2n3g.png",
    "team2_logo": "https://oss.5eplay.com/cloudx/p/sport/csgo/team/chae4nf4nfqe2nie4ung.png",
    "tournament_logo": "https://oss.5eplay.com/cloudx/p/sport/csgo/tournament/d1qr6pcconkt3legerfg.png",
    "estimated_duration": 2.5
  },
  {
    "id": "csgo_mc_2385679",
    "start_timestamp": 1757871000,
    "end_timestamp": 0,
    "start_datetime_utc": "2025-09-14T17:30:00+00:00",
    "end_datetime_utc": "2025-09-14T20:00:00+00:00",
    "tournament": "罗马帝国之声杯 第二季",
    "team1": "SAW",
    "team2": "Gentle Mates",
    "best_type": "BO3",
    "status": "进行中",
    "result": "0-0",
    "status_code": "1",
    "api_status": 1,
    "tournament_id": "csgo_tt_8699",
    "game_type": "CS:GO",
    "grade": "其他",
    "star": "0",
    "bo": "",
    "map_info": "",
    "round_name": "决赛",
    "stage_desc": "淘汰赛 决赛",
    "tournament_stage": "淘汰赛 决赛",
    "team1_logo": "https://oss.5eplay.com/cloudx/p/sport/csgo/team/merge_cldgrokconkqks63cjk0.png",
    "team2_logo": "https://oss.5eplay.com/cloudx/p/sport/csgo/team/d2seh4kconkqbk3bnmvg.png",
    "tournament_logo": "https://oss.5eplay.com/cloudx/p/sport/csgo/tournament/d31ou3sconkqbk3bnnig.png",
    "estimated_duration": 2.5
  },
  {
    "id": "csgo_mc_2385613",
    "start_timestamp": 1757871000,
    "end_timestamp": 0,
    "start_datetime_utc": "2025-09-14T17:30:00+00:00",
    "end_datetime_utc": "2025-09-14T20:00:00+00:00",
    "tournament": "ESEA发展联赛 第54赛季 欧洲",
    "team1": "K27",
    "team2": "Hesta",
    "best_type": "BO3",
    "status": "进行中",
    "result": "0-0",
    "status_code": "1",
    "api_status": 1,
    "tournament_id": "csgo_tt_8676",
    "game_type": "CS:GO",
    "grade": "其他",
    "star": "0",
    "bo": "",
    "map_info": "",
    "round_name": "第5轮",
    "stage_desc": "淘汰赛 败者组 第5轮",
    "tournament_stage": "淘汰赛 败者组 第5轮",
    "team1_logo": "https://oss.5eplay.com/cloudx/p/sport/csgo/team/cqjedmkconkotam7vsp0.png",
    "team2_logo": "https://oss.5eplay.com/cloudx/p/sport/csgo/team/merge_cukvl64conkqmjpn86t0.png",
    "tournament_logo": "https://oss.5eplay.com/sport/csgo/event/8065.png",
    "estimated_duration": 2.5
  },
  {
    "id": "csgo_mc_2385560",
    "start_timestamp": 1757872200,
    "end_timestamp": 0,
    "start_datetime_utc": "2025-09-14T17:50:00+00:00",
    "end_datetime_utc": "2025-09-14T20:20:00+00:00",
    "tournament": "CCT 第3赛季 欧洲系列赛 7 封闭预选赛",
    "team1": "modeame",
    "team2": "1win",
    "best_type": "BO3",
    "status": "进行中",
    "result": "0-0",
    "status_code": "1",
    "api_status": 1,
    "tournament_id": "csgo_tt_8695",
    "game_type": "CS:GO",
    "grade": "",
    "star": "0",
    "bo": "",
    "map_info": "",
    "round_name": "决赛",
    "stage_desc": "小组赛 胜者组 决赛",
    "tournament_stage": "小组赛 胜者组 决赛",
    "team1_logo": "https://oss.5eplay.com/cloudx/p/sport/csgo/team/merge_d13vaccconkt3legekd0.png",
    "team2_logo": "https://oss.5eplay.com/sport/csgo/team/merge_cediu774nfq433414t90.png",
    "tournament_logo": "https://oss.5eplay.com/cloudx/p/sport/csgo/tournament/d0guuusconkt3legeagg.png",
    "estimated_duration": 2.5
  },
  {
    "id": "csgo_mc_2385471",
    "start_timestamp": 1757872800,
    "end_timestamp": 0,
    "start_datetime_utc": "2025-09-14T18:00:00+00:00",
    "end_datetime_utc": "2025-09-14T20:30:00+00:00",
    "tournament": "Betclic Clash 夏季 2025",
    "team1": "FNC",
    "team2": "ECSTATIC",
    "best_type": "BO3",
    "status": "进行中",
    "result": "0-0",
    "status_code": "1",
    "api_status": 1,
    "tournament_id": "csgo_tt_8670",
    "game_type": "CS:GO",
    "grade": "其他",
    "star": "0",
    "bo": "",
    "map_info": "",
    "round_name": "决赛",
    "stage_desc": "淘汰赛 决赛",
    "tournament_stage": "淘汰赛 决赛",
    "team1_logo": "https://oss.5eplay.com/sport/csgo/team/hz/cec3pkn4nfq43340upig.png",
    "team2_logo": "https://oss.5eplay.com/cloudx/p/sport/csgo/team/ch5k0tf4nfqe2nie4ohg.png",
    "tournament_logo": "https://oss.5eplay.com/cloudx/p/sport/csgo/tournament/d2o65gsconkqbk3bnl60.png",
    "estimated_duration": 2.5
  },
  {
    "id": "csgo_mc_2385585",
    "start_timestamp": 1757876400,
    "end_timestamp": 0,
    "start_datetime_utc": "2025-09-14T19:00:00+00:00",
    "end_datetime_utc": "2025-09-14T21:30:00+00:00",
    "tournament": "PrizePicks 北美复兴杯 S9",
    "team1": "Wildcard",
    "team2": "BOSS",
    "best_type": "BO3",
    "status": "未开始",
    "result": "0-0",
    "status_code": "0",
    "api_status": 1,
    "tournament_id": "csgo_tt_8697",
    "game_type": "CS:GO",
    "grade": "其他",
    "star": "0",
    "bo": "",
    "map_info": "",
    "round_name": "半决赛",
    "stage_desc": "淘汰赛 半决赛",
    "tournament_stage": "淘汰赛 半决赛",
    "team1_logo": "https://oss.5eplay.com/cloudx/p/sport/csgo/team/cpsgc7cconklgsjvior0.png",
    "team2_logo": "https://oss.5eplay.com/cloudx/p/sport/csgo/team/cnhsrdkconkqks63ecag.png",
    "tournament_logo": "https://oss.5eplay.com/cloudx/p/sport/csgo/tournament/d07ja74conkt3lege6ug.png",
    "estimated_duration": 2.5
  },
  {
    "id": "csgo_mc_2385594",
    "start_timestamp": 1757876400,
    "end_timestamp": 0,
    "start_datetime_utc": "2025-09-14T19:00:00+00:00",
    "end_datetime_utc": "2025-09-14T21:30:00+00:00",
    "tournament": " CCT 第3赛季 南美系列赛4",
    "team1": "Fluxo",
    "team2": "Players",
    "best_type": "BO3",
    "status": "未开始",
    "result": "0-0",
    "status_code": "0",
    "api_status": 1,
    "tournament_id": "csgo_tt_8681",
    "game_type": "CS:GO",
    "grade": "其他",
    "star": "0",
    "bo": "",
    "map_info": "",
    "round_name": "十六强",
    "stage_desc": "淘汰赛 十六强",
    "tournament_stage": "淘汰赛 十六强",
    "team1_logo": "https://oss.5eplay.com/cloudx/p/sport/csgo/team/merge_cldh3i4conkqks63cjn0.png",
    "team2_logo": "https://oss.5eplay.com/sport/csgo/team/null.png",
    "tournament_logo": "https://oss.5eplay.com/cloudx/p/sport/csgo/tournament/d1vrbfcconkt3leget7g.png",
    "estimated_duration": 2.5
  },
  {
    "id": "csgo_mc_2385586",
    "start_timestamp": 1757887200,
    "end_timestamp": 0,
    "start_datetime_utc": "2025-09-14T22:00:00+00:00",
    "end_datetime_utc": "2025-09-15T00:30:00+00:00",
    "tournament": "PrizePicks 北美复兴杯 S9",
    "team1": "Marsborne",
    "team2": "Getting Info",
    "best_type": "BO3",
    "status": "未开始",
    "result": "0-0",
    "status_code": "0",
    "api_status": 1,
    "tournament_id": "csgo_tt_8697",
    "game_type": "CS:GO",
    "grade": "其他",
    "star": "0",
    "bo": "",
    "map_info": "",
    "round_name": "半决赛",
    "stage_desc": "淘汰赛 半决赛",
    "tournament_stage": "淘汰赛 半决赛",
    "team1_logo": "https://oss.5eplay.com/cloudx/p/sport/csgo/team/cujam3kconkqmjpn84g0.png",
    "team2_logo": "https://oss.5eplay.com/sport/csgo/team/null.png",
    "tournament_logo": "https://oss.5eplay.com/cloudx/p/sport/csgo/tournament/d07ja74conkt3lege6ug.png",
    "estimated_duration": 2.5
  },
  {
    "id": "csgo_mc_2385595",
    "start_timestamp": 1757887200,
    "end_timestamp": 0,
    "start_datetime_utc": "2025-09-14T22:00:00+00:00",
    "end_datetime_utc": "2025-09-15T00:30:00+00:00",
    "tournament": " CCT 第3赛季 南美系列赛4",
    "team1": "BESTIA",
    "team2": "LP",
    "best_type": "BO3",
    "status": "未开始",
    "result": "0-0",
    "status_code": "0",
    "api_status": 1,
    "tournament_id": "csgo_tt_8681",
    "game_type": "CS:GO",
    "grade": "其他",
    "star": "0",
    "bo": "",
    "map_info": "",
    "round_name": "十六强",
    "stage_desc": "淘汰赛 十六强",
    "tournament_stage": "淘汰赛 十六强",
    "team1_logo": "https://oss.5eplay.com/cloudx/p/sport/csgo/team/merge_cgm4vq74nfqe2nie3uc0.png",
    "team2_logo": "https://oss.5eplay.com/sport/csgo/team/null.png",
    "tournament_logo": "https://oss.5eplay.com/cloudx/p/sport/csgo/tournament/d1vrbfcconkt3leget7g.png",
    "estimated_duration": 2.5
  },
  {
    "id": "csgo_mc_2385587",
    "start_timestamp": 1757898000,
    "end_timestamp": 0,
    "start_datetime_utc": "2025-09-15T01:00:00+00:00",
    "end_datetime_utc": "2025-09-15T03:30:00+00:00",
    "tournament": "PrizePicks 北美复兴杯 S9",
    "team1": "TBD",
    "team2": "TBD",
    "best_type": "BO3",
    "status": "未开始",
    "result": "0-0",
    "status_code": "0",
    "api_status": 1,
    "tournament_id": "csgo_tt_8697",
    "game_type": "CS:GO",
    "grade": "其他",
    "star": "0",
    "bo": "",
    "map_info": "",
    "round_name": "总决赛",
    "stage_desc": "淘汰赛 总决赛",
    "tournament_stage": "淘汰赛 总决赛",
    "team1_logo": "https://oss.5eplay.com/sport/csgo/team/merge_cgenhehll806h1bg2rj0.png",
    "team2_logo": "https://oss.5eplay.com/sport/csgo/team/merge_cgenh8pll806h1bg2reg.png",
    "tournament_logo": "https://oss.5eplay.com/cloudx/p/sport/csgo/tournament/d07ja74conkt3lege6ug.png",
    "estimated_duration": 2.5
  },
  {
    "id": "csgo_mc_2385461",
    "start_timestamp": 1757923200,
    "end_timestamp": 0,
    "start_datetime_utc": "2025-09-15T08:00:00+00:00",
    "end_datetime_utc": "2025-09-15T10:30:00+00:00",
    "tournament": "Exort试验场 第四季",
    "team1": "CPH Wolves",
    "team2": "SENZA",
    "best_type": "BO3",
    "status": "未开始",
    "result": "0-0",
    "status_code": "0",
    "api_status": 1,
    "tournament_id": "csgo_tt_8692",
    "game_type": "CS:GO",
    "grade": "C级",
    "star": "0",
    "bo": "",
    "map_info": "",
    "round_name": "第二轮",
    "stage_desc": "小组赛 第二轮",
    "tournament_stage": "小组赛 第二轮",
    "team1_logo": "https://oss.5eplay.com/sport/csgo/team/hz/cec3pfv4nfq43340unug.png",
    "team2_logo": "https://oss.5eplay.com/cloudx/p/sport/csgo/team/merge_d2udrp4conkqbk3bnnb0.png",
    "tournament_logo": "https://oss.5eplay.com/cloudx/p/sport/csgo/tournament/d0trhpcconkt3legef50.png",
    "estimated_duration": 2.5
  },
  {
    "id": "csgo_mc_2385306",
    "start_timestamp": 1757923200,
    "end_timestamp": 0,
    "start_datetime_utc": "2025-09-15T08:00:00+00:00",
    "end_datetime_utc": "2025-09-15T10:30:00+00:00",
    "tournament": "FISSURE 裂变天地 2",
    "team1": "TBD",
    "team2": "TBD",
    "best_type": "BO3",
    "status": "未开始",
    "result": "0-0",
    "status_code": "0",
    "api_status": 1,
    "tournament_id": "csgo_tt_8064",
    "game_type": "CS:GO",
    "grade": "A级",
    "star": "1",
    "bo": "",
    "map_info": "",
    "round_name": "第三轮",
    "stage_desc": "小组赛 第三轮",
    "tournament_stage": "小组赛 第三轮",
    "team1_logo": "https://oss.5eplay.com/sport/csgo/team/merge_cgenhehll806h1bg2rj0.png",
    "team2_logo": "https://oss.5eplay.com/sport/csgo/team/merge_cgenh8pll806h1bg2reg.png",
    "tournament_logo": "https://oss.5eplay.com/cloudx/p/sport/csgo/tournament/d1qr6pcconkt3legerfg.png",
    "estimated_duration": 2.5
  },
  {
    "id": "csgo_mc_2385307",
    "start_timestamp": 1757923200,
    "end_timestamp": 0,
    "start_datetime_utc": "2025-09-15T08:00:00+00:00",
    "end_datetime_utc": "2025-09-15T10:30:00+00:00",
    "tournament": "FISSURE 裂变天地 2",
    "team1": "TBD",
    "team2": "TBD",
    "best_type": "BO3",
    "status": "未开始",
    "result": "0-0",
    "status_code": "0",
    "api_status": 1,
    "tournament_id": "csgo_tt_8064",
    "game_type": "CS:GO",
    "grade": "A级",
    "star": "1",
    "bo": "",
    "map_info": "",
    "round_name": "第三轮",
    "stage_desc": "小组赛 第三轮",
    "tournament_stage": "小组赛 第三轮",
    "team1_logo": "https://oss.5eplay.com/sport/csgo/team/merge_cgenhehll806h1bg2rj0.png",
    "team2_logo": "https://oss.5eplay.com/sport/csgo/team/merge_cgenh8pll806h1bg2reg.png",
    "tournament_logo": "https://oss.5eplay.com/cloudx/p/sport/csgo/tournament/d1qr6pcconkt3legerfg.png",
    "estimated_duration": 2.5
  },
  {
    "id": "csgo_mc_2385553",
    "start_timestamp": 1757925000,
    "end_timestamp": 0,
    "start_datetime_utc": "2025-09-15T08:30:00+00:00",
    "end_datetime_utc": "2025-09-15T11:00:00+00:00",
    "tournament": "CCT 第3赛季 欧洲系列赛 7 封闭预选赛",
    "team1": "Reason",
    "team2": "Leo",
    "best_type": "BO3",
    "status": "未开始",
    "result": "0-0",
    "status_code": "0",
    "api_status": 1,
    "tournament_id": "csgo_tt_8695",
    "game_type": "CS:GO",
    "grade": "",
    "star": "0",
    "bo": "",
    "map_info": "",
    "round_name": "首轮",
    "stage_desc": "小组赛 胜者组 首轮",
    "tournament_stage": "小组赛 胜者组 首轮",
    "team1_logo": "https://oss.5eplay.com/sport/csgo/team/hz/cec3pj74nfq43340up1g.png",
    "team2_logo": "https://oss.5eplay.com/cloudx/p/sport/csgo/team/cu94sf4conkqmjpn80og.png",
    "tournament_logo": "https://oss.5eplay.com/cloudx/p/sport/csgo/tournament/d0guuusconkt3legeagg.png",
    "estimated_duration": 2.5
  },
  {
    "id": "csgo_mc_2385262",
    "start_timestamp": 1757932200,
    "end_timestamp": 0,
    "start_datetime_utc": "2025-09-15T10:30:00+00:00",
    "end_datetime_utc": "2025-09-15T13:00:00+00:00",
    "tournament": "欧洲职业联赛 系列赛2",
    "team1": "CPH Wolves",
    "team2": "Metizport",
    "best_type": "BO3",
    "status": "未开始",
    "result": "0-0",
    "status_code": "0",
    "api_status": 1,
    "tournament_id": "csgo_tt_8660",
    "game_type": "CS:GO",
    "grade": "其他",
    "star": "0",
    "bo": "",
    "map_info": "",
    "round_name": "决赛",
    "stage_desc": "小组赛 败者组 决赛",
    "tournament_stage": "小组赛 败者组 决赛",
    "team1_logo": "https://oss.5eplay.com/sport/csgo/team/hz/cec3pfv4nfq43340unug.png",
    "team2_logo": "https://oss.5eplay.com/cloudx/p/sport/csgo/team/merge_crl43ekconkotam80sdg.png",
    "tournament_logo": "https://oss.5eplay.com/cloudx/p/sport/csgo/tournament/cqtimtcconkotam80b90.png",
    "estimated_duration": 2.5
  },
  {
    "id": "csgo_mc_2385462",
    "start_timestamp": 1757934000,
    "end_timestamp": 0,
    "start_datetime_utc": "2025-09-15T11:00:00+00:00",
    "end_datetime_utc": "2025-09-15T13:30:00+00:00",
    "tournament": "Exort试验场 第四季",
    "team1": "ESC",
    "team2": "Aab",
    "best_type": "BO3",
    "status": "未开始",
    "result": "0-0",
    "status_code": "0",
    "api_status": 1,
    "tournament_id": "csgo_tt_8692",
    "game_type": "CS:GO",
    "grade": "C级",
    "star": "0",
    "bo": "",
    "map_info": "",
    "round_name": "第二轮",
    "stage_desc": "小组赛 第二轮",
    "tournament_stage": "小组赛 第二轮",
    "team1_logo": "https://oss.5eplay.com/cloudx/p/sport/csgo/team/cnl75mkconklgsjvgk1g.png",
    "team2_logo": "https://oss.5eplay.com/sport/csgo/team/hz/cec3tof4nfq43340vki0.png",
    "tournament_logo": "https://oss.5eplay.com/cloudx/p/sport/csgo/tournament/d0trhpcconkt3legef50.png",
    "estimated_duration": 2.5
  },
  {
    "id": "csgo_mc_2385617",
    "start_timestamp": 1757934000,
    "end_timestamp": 0,
    "start_datetime_utc": "2025-09-15T11:00:00+00:00",
    "end_datetime_utc": "2025-09-15T13:30:00+00:00",
    "tournament": "CCT 第3赛季 欧洲系列赛 6",
    "team1": "TBD",
    "team2": "TBD",
    "best_type": "BO3",
    "status": "未开始",
    "result": "0-0",
    "status_code": "0",
    "api_status": 1,
    "tournament_id": "csgo_tt_8680",
    "game_type": "CS:GO",
    "grade": "C级",
    "star": "0",
    "bo": "",
    "map_info": "",
    "round_name": "第四轮",
    "stage_desc": "小组赛 第四轮",
    "tournament_stage": "小组赛 第四轮",
    "team1_logo": "https://oss.5eplay.com/sport/csgo/team/merge_cgenhehll806h1bg2rj0.png",
    "team2_logo": "https://oss.5eplay.com/sport/csgo/team/merge_cgenh8pll806h1bg2reg.png",
    "tournament_logo": "https://oss.5eplay.com/cloudx/p/sport/csgo/tournament/d0guuusconkt3legeagg.png",
    "estimated_duration": 2.5
  },
  {
    "id": "csgo_mc_2385554",
    "start_timestamp": 1757935800,
    "end_timestamp": 0,
    "start_datetime_utc": "2025-09-15T11:30:00+00:00",
    "end_datetime_utc": "2025-09-15T14:00:00+00:00",
    "tournament": "CCT 第3赛季 欧洲系列赛 7 封闭预选赛",
    "team1": "Imperial fe",
    "team2": "QMISTRY",
    "best_type": "BO3",
    "status": "未开始",
    "result": "0-0",
    "status_code": "0",
    "api_status": 1,
    "tournament_id": "csgo_tt_8695",
    "game_type": "CS:GO",
    "grade": "",
    "star": "0",
    "bo": "",
    "map_info": "",
    "round_name": "首轮",
    "stage_desc": "小组赛 胜者组 首轮",
    "tournament_stage": "小组赛 胜者组 首轮",
    "team1_logo": "https://oss.5eplay.com/sport/csgo/team/12828.png",
    "team2_logo": "https://oss.5eplay.com/cloudx/p/sport/csgo/team/d01k7m4conkt3lege5fg.png",
    "tournament_logo": "https://oss.5eplay.com/cloudx/p/sport/csgo/tournament/d0guuusconkt3legeagg.png",
    "estimated_duration": 2.5
  },
  {
    "id": "csgo_mc_2385308",
    "start_timestamp": 1757935800,
    "end_timestamp": 0,
    "start_datetime_utc": "2025-09-15T11:30:00+00:00",
    "end_datetime_utc": "2025-09-15T14:00:00+00:00",
    "tournament": "FISSURE 裂变天地 2",
    "team1": "TBD",
    "team2": "TBD",
    "best_type": "BO3",
    "status": "未开始",
    "result": "0-0",
    "status_code": "0",
    "api_status": 1,
    "tournament_id": "csgo_tt_8064",
    "game_type": "CS:GO",
    "grade": "A级",
    "star": "1",
    "bo": "",
    "map_info": "",
    "round_name": "第三轮",
    "stage_desc": "小组赛 第三轮",
    "tournament_stage": "小组赛 第三轮",
    "team1_logo": "https://oss.5eplay.com/sport/csgo/team/merge_cgenhehll806h1bg2rj0.png",
    "team2_logo": "https://oss.5eplay.com/sport/csgo/team/merge_cgenh8pll806h1bg2reg.png",
    "tournament_logo": "https://oss.5eplay.com/cloudx/p/sport/csgo/tournament/d1qr6pcconkt3legerfg.png",
    "estimated_duration": 2.5
  },
  {
    "id": "csgo_mc_2385309",
    "start_timestamp": 1757935800,
    "end_timestamp": 0,
    "start_datetime_utc": "2025-09-15T11:30:00+00:00",
    "end_datetime_utc": "2025-09-15T14:00:00+00:00",
    "tournament": "FISSURE 裂变天地 2",
    "team1": "TBD",
    "team2": "TBD",
    "best_type": "BO3",
    "status": "未开始",
    "result": "0-0",
    "status_code": "0",
    "api_status": 1,
    "tournament_id": "csgo_tt_8064",
    "game_type": "CS:GO",
    "grade": "A级",
    "star": "1",
    "bo": "",
    "map_info": "",
    "round_name": "第三轮",
    "stage_desc": "小组赛 第三轮",
    "tournament_stage": "小组赛 第三轮",
    "team1_logo": "https://oss.5eplay.com/sport/csgo/team/merge_cgenhehll806h1bg2rj0.png",
    "team2_logo": "https://oss.5eplay.com/sport/csgo/team/merge_cgenh8pll806h1bg2reg.png",
    "tournament_logo": "https://oss.5eplay.com/cloudx/p/sport/csgo/tournament/d1qr6pcconkt3legerfg.png",
    "estimated_duration": 2.5
  },
  {
    "id": "csgo_mc_2385261",
    "start_timestamp": 1757941200,
    "end_timestamp": 0,
    "start_datetime_utc": "2025-09-15T13:00:00+00:00",
    "end_datetime_utc": "2025-09-15T15:30:00+00:00",
    "tournament": "欧洲职业联赛 系列赛2",
    "team1": "EF",
    "team2": "SENZA",
    "best_type": "BO3",
    "status": "未开始",
    "result": "0-0",
    "status_code": "0",
    "api_status": 1,
    "tournament_id": "csgo_tt_8660",
    "game_type": "CS:GO",
    "grade": "其他",
    "star": "0",
    "bo": "",
    "map_info": "",
    "round_name": "决赛",
    "stage_desc": "小组赛 败者组 决赛",
    "tournament_stage": "小组赛 败者组 决赛",
    "team1_logo": "https://oss.5eplay.com/cloudx/p/sport/csgo/team/cla5secconkqks63cgbg.png",
    "team2_logo": "https://oss.5eplay.com/cloudx/p/sport/csgo/team/merge_d2udrp4conkqbk3bnnb0.png",
    "tournament_logo": "https://oss.5eplay.com/cloudx/p/sport/csgo/tournament/cqtimtcconkotam80b90.png",
    "estimated_duration": 2.5
  },
  {
    "id": "csgo_mc_2385596",
    "start_timestamp": 1757941200,
    "end_timestamp": 0,
    "start_datetime_utc": "2025-09-15T13:00:00+00:00",
    "end_datetime_utc": "2025-09-15T15:30:00+00:00",
    "tournament": " CCT 第3赛季 南美系列赛4",
    "team1": "TBD",
    "team2": "TBD",
    "best_type": "BO3",
    "status": "未开始",
    "result": "0-0",
    "status_code": "0",
    "api_status": 1,
    "tournament_id": "csgo_tt_8681",
    "game_type": "CS:GO",
    "grade": "其他",
    "star": "0",
    "bo": "",
    "map_info": "",
    "round_name": "八强",
    "stage_desc": "淘汰赛 八强",
    "tournament_stage": "淘汰赛 八强",
    "team1_logo": "https://oss.5eplay.com/sport/csgo/team/merge_cgenhehll806h1bg2rj0.png",
    "team2_logo": "https://oss.5eplay.com/sport/csgo/team/merge_cgenh8pll806h1bg2reg.png",
    "tournament_logo": "https://oss.5eplay.com/cloudx/p/sport/csgo/tournament/d1vrbfcconkt3leget7g.png",
    "estimated_duration": 2.5
  },
  {
    "id": "csgo_mc_2385463",
    "start_timestamp": 1757944800,
    "end_timestamp": 0,
    "start_datetime_utc": "2025-09-15T14:00:00+00:00",
    "end_datetime_utc": "2025-09-15T16:30:00+00:00",
    "tournament": "Exort试验场 第四季",
    "team1": "Monte",
    "team2": "Johnny Speeds",
    "best_type": "BO3",
    "status": "未开始",
    "result": "0-0",
    "status_code": "0",
    "api_status": 1,
    "tournament_id": "csgo_tt_8692",
    "game_type": "CS:GO",
    "grade": "C级",
    "star": "0",
    "bo": "",
    "map_info": "",
    "round_name": "第二轮",
    "stage_desc": "小组赛 第二轮",
    "tournament_stage": "小组赛 第二轮",
    "team1_logo": "https://oss.5eplay.com/cloudx/p/sport/csgo/team/chae1nv4nfqe2nie4ul0.png",
    "team2_logo": "https://oss.5eplay.com/cloudx/p/sport/csgo/team/cs3ihv4conkotam815t0.png",
    "tournament_logo": "https://oss.5eplay.com/cloudx/p/sport/csgo/tournament/d0trhpcconkt3legef50.png",
    "estimated_duration": 2.5
  },
  {
    "id": "csgo_mc_2385535",
    "start_timestamp": 1757944800,
    "end_timestamp": 0,
    "start_datetime_utc": "2025-09-15T14:00:00+00:00",
    "end_datetime_utc": "2025-09-15T16:30:00+00:00",
    "tournament": "银河之战 2025 第4阶段 公开预选",
    "team1": "Anonymo",
    "team2": "AMKAL",
    "best_type": "BO3",
    "status": "未开始",
    "result": "0-0",
    "status_code": "0",
    "api_status": 1,
    "tournament_id": "csgo_tt_8691",
    "game_type": "CS:GO",
    "grade": "其他",
    "star": "0",
    "bo": "",
    "map_info": "",
    "round_name": "决赛",
    "stage_desc": "小组赛 胜者组 决赛",
    "tournament_stage": "小组赛 胜者组 决赛",
    "team1_logo": "https://oss.5eplay.com/sport/csgo/team/merge_ceihfkv4nfq4334151l0.png",
    "team2_logo": "https://oss.5eplay.com/cloudx/p/sport/csgo/team/merge_cm76vusconkqks63d6i0.png",
    "tournament_logo": "https://oss.5eplay.com/cloudx/p/sport/csgo/tournament/d140b3kconkt3legekmg.png",
    "estimated_duration": 2.5
  },
  {
    "id": "csgo_mc_2385618",
    "start_timestamp": 1757944800,
    "end_timestamp": 0,
    "start_datetime_utc": "2025-09-15T14:00:00+00:00",
    "end_datetime_utc": "2025-09-15T16:30:00+00:00",
    "tournament": "CCT 第3赛季 欧洲系列赛 6",
    "team1": "TBD",
    "team2": "TBD",
    "best_type": "BO3",
    "status": "未开始",
    "result": "0-0",
    "status_code": "0",
    "api_status": 1,
    "tournament_id": "csgo_tt_8680",
    "game_type": "CS:GO",
    "grade": "C级",
    "star": "0",
    "bo": "",
    "map_info": "",
    "round_name": "第四轮",
    "stage_desc": "小组赛 第四轮",
    "tournament_stage": "小组赛 第四轮",
    "team1_logo": "https://oss.5eplay.com/sport/csgo/team/merge_cgenhehll806h1bg2rj0.png",
    "team2_logo": "https://oss.5eplay.com/sport/csgo/team/merge_cgenh8pll806h1bg2reg.png",
    "tournament_logo": "https://oss.5eplay.com/cloudx/p/sport/csgo/tournament/d0guuusconkt3legeagg.png",
    "estimated_duration": 2.5
  },
  {
    "id": "csgo_mc_2385555",
    "start_timestamp": 1757946600,
    "end_timestamp": 0,
    "start_datetime_utc": "2025-09-15T14:30:00+00:00",
    "end_datetime_utc": "2025-09-15T17:00:00+00:00",
    "tournament": "CCT 第3赛季 欧洲系列赛 7 封闭预选赛",
    "team1": "Khan",
    "team2": "Wildcard Academy",
    "best_type": "BO3",
    "status": "未开始",
    "result": "0-0",
    "status_code": "0",
    "api_status": 1,
    "tournament_id": "csgo_tt_8695",
    "game_type": "CS:GO",
    "grade": "",
    "star": "0",
    "bo": "",
    "map_info": "",
    "round_name": "首轮",
    "stage_desc": "小组赛 胜者组 首轮",
    "tournament_stage": "小组赛 胜者组 首轮",
    "team1_logo": "https://oss.5eplay.com/cloudx/p/sport/csgo/team/merge_d2gk2gkconkt3legf0v0.png",
    "team2_logo": "https://oss.5eplay.com/cloudx/p/sport/csgo/team/cv1k8dsconkqmjpn8ep0.png",
    "tournament_logo": "https://oss.5eplay.com/cloudx/p/sport/csgo/tournament/d0guuusconkt3legeagg.png",
    "estimated_duration": 2.5
  },
  {
    "id": "csgo_mc_2385311",
    "start_timestamp": 1757948400,
    "end_timestamp": 0,
    "start_datetime_utc": "2025-09-15T15:00:00+00:00",
    "end_datetime_utc": "2025-09-15T17:30:00+00:00",
    "tournament": "FISSURE 裂变天地 2",
    "team1": "TBD",
    "team2": "TBD",
    "best_type": "BO3",
    "status": "未开始",
    "result": "0-0",
    "status_code": "0",
    "api_status": 1,
    "tournament_id": "csgo_tt_8064",
    "game_type": "CS:GO",
    "grade": "A级",
    "star": "1",
    "bo": "",
    "map_info": "",
    "round_name": "第三轮",
    "stage_desc": "小组赛 第三轮",
    "tournament_stage": "小组赛 第三轮",
    "team1_logo": "https://oss.5eplay.com/sport/csgo/team/merge_cgenhehll806h1bg2rj0.png",
    "team2_logo": "https://oss.5eplay.com/sport/csgo/team/merge_cgenh8pll806h1bg2reg.png",
    "tournament_logo": "https://oss.5eplay.com/cloudx/p/sport/csgo/tournament/d1qr6pcconkt3legerfg.png",
    "estimated_duration": 2.5
  },
  {
    "id": "csgo_mc_2385310",
    "start_timestamp": 1757948400,
    "end_timestamp": 0,
    "start_datetime_utc": "2025-09-15T15:00:00+00:00",
    "end_datetime_utc": "2025-09-15T17:30:00+00:00",
    "tournament": "FISSURE 裂变天地 2",
    "team1": "TBD",
    "team2": "TBD",
    "best_type": "BO3",
    "status": "未开始",
    "result": "0-0",
    "status_code": "0",
    "api_status": 1,
    "tournament_id": "csgo_tt_8064",
    "game_type": "CS:GO",
    "grade": "A级",
    "star": "1",
    "bo": "",
    "map_info": "",
    "round_name": "第三轮",
    "stage_desc": "小组赛 第三轮",
    "tournament_stage": "小组赛 第三轮",
    "team1_logo": "https://oss.5eplay.com/sport/csgo/team/merge_cgenhehll806h1bg2rj0.png",
    "team2_logo": "https://oss.5eplay.com/sport/csgo/team/merge_cgenh8pll806h1bg2reg.png",
    "tournament_logo": "https://oss.5eplay.com/cloudx/p/sport/csgo/tournament/d1qr6pcconkt3legerfg.png",
    "estimated_duration": 2.5
  },
  {
    "id": "csgo_mc_2385597",
    "start_timestamp": 1757952000,
    "end_timestamp": 0,
    "start_datetime_utc": "2025-09-15T16:00:00+00:00",
    "end_datetime_utc": "2025-09-15T18:30:00+00:00",
    "tournament": " CCT 第3赛季 南美系列赛4",
    "team1": "TBD",
    "team2": "TBD",
    "best_type": "BO3",
    "status": "未开始",
    "result": "0-0",
    "status_code": "0",
    "api_status": 1,
    "tournament_id": "csgo_tt_8681",
    "game_type": "CS:GO",
    "grade": "其他",
    "star": "0",
    "bo": "",
    "map_info": "",
    "round_name": "八强",
    "stage_desc": "淘汰赛 八强",
    "tournament_stage": "淘汰赛 八强",
    "team1_logo": "https://oss.5eplay.com/sport/csgo/team/merge_cgenhehll806h1bg2rj0.png",
    "team2_logo": "https://oss.5eplay.com/sport/csgo/team/merge_cgenh8pll806h1bg2reg.png",
    "tournament_logo": "https://oss.5eplay.com/cloudx/p/sport/csgo/tournament/d1vrbfcconkt3leget7g.png",
    "estimated_duration": 2.5
  },
  {
    "id": "csgo_mc_2385464",
    "start_timestamp": 1757955600,
    "end_timestamp": 0,
    "start_datetime_utc": "2025-09-15T17:00:00+00:00",
    "end_datetime_utc": "2025-09-15T19:30:00+00:00",
    "tournament": "Exort试验场 第四季",
    "team1": "SINNERS",
    "team2": "Partizan",
    "best_type": "BO3",
    "status": "未开始",
    "result": "0-0",
    "status_code": "0",
    "api_status": 1,
    "tournament_id": "csgo_tt_8692",
    "game_type": "CS:GO",
    "grade": "C级",
    "star": "0",
    "bo": "",
    "map_info": "",
    "round_name": "第二轮",
    "stage_desc": "小组赛 第二轮",
    "tournament_stage": "小组赛 第二轮",
    "team1_logo": "https://oss.5eplay.com/sport/csgo/team/hz/cec3uq74nfq43340vq30.png",
    "team2_logo": "https://oss.5eplay.com/sport/csgo/team/hz/cec409f4nfq4334102ng.png",
    "tournament_logo": "https://oss.5eplay.com/cloudx/p/sport/csgo/tournament/d0trhpcconkt3legef50.png",
    "estimated_duration": 2.5
  },
  {
    "id": "csgo_mc_2385536",
    "start_timestamp": 1757955600,
    "end_timestamp": 0,
    "start_datetime_utc": "2025-09-15T17:00:00+00:00",
    "end_datetime_utc": "2025-09-15T19:30:00+00:00",
    "tournament": "银河之战 2025 第4阶段 公开预选",
    "team1": "SENZA",
    "team2": "500",
    "best_type": "BO3",
    "status": "未开始",
    "result": "0-0",
    "status_code": "0",
    "api_status": 1,
    "tournament_id": "csgo_tt_8691",
    "game_type": "CS:GO",
    "grade": "其他",
    "star": "0",
    "bo": "",
    "map_info": "",
    "round_name": "首轮",
    "stage_desc": "小组赛 败者组 首轮",
    "tournament_stage": "小组赛 败者组 首轮",
    "team1_logo": "https://oss.5eplay.com/cloudx/p/sport/csgo/team/merge_d2udrp4conkqbk3bnnb0.png",
    "team2_logo": "https://oss.5eplay.com/cloudx/p/sport/csgo/team/crggp64conkotam80pb0.png",
    "tournament_logo": "https://oss.5eplay.com/cloudx/p/sport/csgo/tournament/d140b3kconkt3legekmg.png",
    "estimated_duration": 2.5
  },
  {
    "id": "csgo_mc_2385619",
    "start_timestamp": 1757955600,
    "end_timestamp": 0,
    "start_datetime_utc": "2025-09-15T17:00:00+00:00",
    "end_datetime_utc": "2025-09-15T19:30:00+00:00",
    "tournament": "CCT 第3赛季 欧洲系列赛 6",
    "team1": "TBD",
    "team2": "TBD",
    "best_type": "BO3",
    "status": "未开始",
    "result": "0-0",
    "status_code": "0",
    "api_status": 1,
    "tournament_id": "csgo_tt_8680",
    "game_type": "CS:GO",
    "grade": "C级",
    "star": "0",
    "bo": "",
    "map_info": "",
    "round_name": "第四轮",
    "stage_desc": "小组赛 第四轮",
    "tournament_stage": "小组赛 第四轮",
    "team1_logo": "https://oss.5eplay.com/sport/csgo/team/merge_cgenhehll806h1bg2rj0.png",
    "team2_logo": "https://oss.5eplay.com/sport/csgo/team/merge_cgenh8pll806h1bg2reg.png",
    "tournament_logo": "https://oss.5eplay.com/cloudx/p/sport/csgo/tournament/d0guuusconkt3legeagg.png",
    "estimated_duration": 2.5
  },
  {
    "id": "csgo_mc_2385556",
    "start_timestamp": 1757957400,
    "end_timestamp": 0,
    "start_datetime_utc": "2025-09-15T17:30:00+00:00",
    "end_datetime_utc": "2025-09-15T20:00:00+00:00",
    "tournament": "CCT 第3赛季 欧洲系列赛 7 封闭预选赛",
    "team1": "m1x",
    "team2": "UNiTY",
    "best_type": "BO3",
    "status": "未开始",
    "result": "0-0",
    "status_code": "0",
    "api_status": 1,
    "tournament_id": "csgo_tt_8695",
    "game_type": "CS:GO",
    "grade": "",
    "star": "0",
    "bo": "",
    "map_info": "",
    "round_name": "首轮",
    "stage_desc": "小组赛 胜者组 首轮",
    "tournament_stage": "小组赛 胜者组 首轮",
    "team1_logo": "https://oss.5eplay.com/sport/csgo/team/null.png",
    "team2_logo": "https://oss.5eplay.com/cloudx/p/sport/csgo/team/cjrh38cconkqks63b5a0.png",
    "tournament_logo": "https://oss.5eplay.com/cloudx/p/sport/csgo/tournament/d0guuusconkt3legeagg.png",
    "estimated_duration": 2.5
  },
  {
    "id": "csgo_mc_2385312",
    "start_timestamp": 1757961000,
    "end_timestamp": 0,
    "start_datetime_utc": "2025-09-15T18:30:00+00:00",
    "end_datetime_utc": "2025-09-15T21:00:00+00:00",
    "tournament": "FISSURE 裂变天地 2",
    "team1": "TBD",
    "team2": "TBD",
    "best_type": "BO3",
    "status": "未开始",
    "result": "0-0",
    "status_code": "0",
    "api_status": 1,
    "tournament_id": "csgo_tt_8064",
    "game_type": "CS:GO",
    "grade": "A级",
    "star": "1",
    "bo": "",
    "map_info": "",
    "round_name": "第三轮",
    "stage_desc": "小组赛 第三轮",
    "tournament_stage": "小组赛 第三轮",
    "team1_logo": "https://oss.5eplay.com/sport/csgo/team/merge_cgenhehll806h1bg2rj0.png",
    "team2_logo": "https://oss.5eplay.com/sport/csgo/team/merge_cgenh8pll806h1bg2reg.png",
    "tournament_logo": "https://oss.5eplay.com/cloudx/p/sport/csgo/tournament/d1qr6pcconkt3legerfg.png",
    "estimated_duration": 2.5
  }
]